Workbook

Sheet ilustração
A1: retranca | B1: status | C1: categoria | D1: localizacao | E1: pagina | F1: volume | G1: unidade | H1: capitulo_secao | I1: tipo | J1: NOME DA OBRA PARA RESGATE | K1: PÁGINA PARA RESGATE | L1: VOLUME PARA RESGATE | M1: VERSÃO PARA RESGATE | N1: PROPRIEDADE | O1: descricao | P1: observacao_edit_nuc | Q1: lote | R1: data_liberacao_para_arte | S1: data_envio_pedido | T1: data_recebimento_rafe | U1: data_retorno_rafe | V1: data_recebimento_finalizada | W1: sigla | X1: ilustrador | Y1: ilustrador_ajuste | Z1: credito | AA1: classificacao | AB1: observacao_arte | AC1: pagamento | AD1: projeto | AE1: componente | AF1: ilustrador_resgate
A2: i0198zz_3p011m_g27_e001 | B2: APLICADA | C2: IL TEC ARTE | D2: MIOLO | E2: 25 | F2: 3 | G2: 1 | I2: AJUSTE | O2: Ilustração de uma tabela em folha de caderno (trocou o código, é a mesma da i01153p011m que foi excluída) | S2: 45860 | V2: 45860 | W2: zz | X2: =IF(Tabela2[[#This Row],[sigla]]="","",VLOOKUP(Tabela2[[#This Row],[sigla]],créditos_base!B:C,2,0)) -> VER DOCUMENTO DE ILS. TÉCNICAS | Y2: Arte | Z2: VINÍCIUS COSTA/ARQUIVO DA EDITORA | AA2: 13 | AB2: resgate com ajuste | AC2: FINALIZADO | AD2: ="Pitanguá" -> Pitanguá | AE2: ="Matemática" -> Matemática
A3: 1318_3p011m_g27_e001 | B3: APLICADA | C3: IL TEC ARTE | D3: MIOLO | E3: 137 | F3: 3 | G3: 7 | I3: RESGATE | O3: Resgatar ilustração de um short azul, da página 137 do g23_mdn_lt_3npm. Código antigo i1406rn_3pmm_g19_mdn | W3: rn | X3: =IF(Tabela2[[#This Row],[sigla]]="","",VLOOKUP(Tabela2[[#This Row],[sigla]],créditos_base!B:C,2,0)) -> RAFAEL L. GAION/ARQUIVO DA EDITORA | Z3: =Tabela2[[#This Row],[ilustrador]] -> RAFAEL L. GAION/ARQUIVO DA EDITORA | AD3: ="Pitanguá" -> Pitanguá | AE3: ="Matemática" -> Matemática
A4: g0104_3p011m_g27_e001 | B4: APLICADA | C4: GRÁFICO | D4: MIOLO | E4: 14 | F4: 3 | G4: 1 | I4: AJUSTE | O4: resgatar gráfico com a cor preferida dos estudantes do g23_mdn_lt_3npm_p014 código antigo gt0209sl_3pmm_g19_mdn AJUSTE: No gráfico, trocar "Quantidade de alunos" por "Quantidade de estudantes". Inserir fio contorno preto nas barras do grafico. | Q4: 78 | R4: 45820 | S4: 45825 | V4: 45826 | W4: sl | X4: =IF(Tabela2[[#This Row],[sigla]]="","",VLOOKUP(Tabela2[[#This Row],[sigla]],créditos_base!B:C,2,0)) -> SERGIO LIMA/ARQUIVO DA EDITORA | Y4: Rebecca Baniski | Z4: =Tabela2[[#This Row],[ilustrador]] -> SERGIO LIMA/ARQUIVO DA EDITORA | AA4: 13 | AB4: resgate com ajuste | AC4: FINALIZADO | AD4: ="Pitanguá" -> Pitanguá | AE4: ="Matemática" -> Matemática
A5: g0112_5p011m_g27_e001 | B5: APLICADA | C5: GRÁFICO | D5: MIOLO | E5: 22 | F5: 5 | G5: 1 | I5: AJUSTE | O5: Resgatar ilustração de um gráfico de personalidades brasileiras com barras horizontais. Veio de: g23_mdn_lt_5npm_p014. Código antigo: i0210ri_5pmm_g19_mdn AJUSTE: atualizar para novo padrão, compondo fio preto nas barras | Q5: 126 | R5: 45863 | S5: 45867 | V5: 45869 | W5: ri | X5: =IF(Tabela2[[#This Row],[sigla]]="","",VLOOKUP(Tabela2[[#This Row],[sigla]],créditos_base!B:C,2,0)) -> RONALDO LUCENA/ARQUIVO DA EDITORA | Y5: Arte | Z5: =Tabela2[[#This Row],[ilustrador]] -> RONALDO LUCENA/ARQUIVO DA EDITORA | AA5: 13 | AB5: RESGATE COM AJUSTAE | AC5: FINALIZADO | AD5: ="Pitanguá" -> Pitanguá | AE5: ="Matemática" -> Matemática
A6: g0116_3p011m_g27_e001 | B6: APLICADA | C6: GRÁFICO | D6: MIOLO | E6: 194 | F6: 3 | G6: 1 | I6: AJUSTE | O6: Resgatar gráfico/ilustração pesquisa dos estudantes; g23_mdn_lt_3npm_p194; código antigo gt3413sl_3npm_g23_mdn_aj AJUSTE. Trocara alunos para estudantes no eixo vertical e inserir fio contorno preto nas barras do grafico. | Q6: 78 | R6: 45820 | S6: 45831 | V6: 45831 | W6: sl | X6: =IF(Tabela2[[#This Row],[sigla]]="","",VLOOKUP(Tabela2[[#This Row],[sigla]],créditos_base!B:C,2,0)) -> SERGIO LIMA/ARQUIVO DA EDITORA | Y6: Ingridhi Borges | Z6: =Tabela2[[#This Row],[ilustrador]] -> SERGIO LIMA/ARQUIVO DA EDITORA | AA6: 13 | AB6: RESGATE COM AJUSTE | AC6: FINALIZADO | AD6: ="Pitanguá" -> Pitanguá | AE6: ="Matemática" -> Matemática
A7: g0118_3p011m_g27_e001 | B7: APLICADA | C7: GRÁFICO | D7: MIOLO | E7: 197 | F7: 3 | G7: 1 | I7: AJUSTE | O7: Resgatar gráfico/ilustração de moradores por quantidade de residências; g23_mdn_lt_3npm_p197; código antigo gt3415sl_3npm_g23_mdn_aj | Q7: 164 | R7: 45892 | S7: 45894 | V7: 45894 | W7: sl | X7: =IF(Tabela2[[#This Row],[sigla]]="","",VLOOKUP(Tabela2[[#This Row],[sigla]],créditos_base!B:C,2,0)) -> SERGIO LIMA/ARQUIVO DA EDITORA | Y7: Maryane Vioto Silva | Z7: =Tabela2[[#This Row],[ilustrador]] -> SERGIO LIMA/ARQUIVO DA EDITORA | AA7: 14 | AB7: Resgate com ajuste | AC7: FINALIZADO | AD7: ="Pitanguá" -> Pitanguá | AE7: ="Matemática" -> Matemática
A8: g0124_5p011m_g27_e001 | B8: APLICADA | C8: GRÁFICO | D8: MIOLO | E8: 30 | F8: 5 | G8: 1 | I8: NOVA | O8: Ilustração de parte de um gráfico de colunas verticais, como a ref. Nesse gráfico, os bairros devem ser A, B, C e D, porém deve-se compor apenas as barras de A e B. A barra de A deve representar 300 kg e a de B, 700 kg. A escala do eixo vertical deve ser graduada de 100 em 100, com início em 0 e fim em 1 000. O eixo vertical deve ser nomeado por “Quantidade (em kg)” e o horizontal, “Bairro”. O restante do gráfico será preenchido pelo estudante. | Q8: 126 | R8: 45863 | S8: 45867 | V8: 45869 | W8: ib | X8: =IF(Tabela2[[#This Row],[sigla]]="","",VLOOKUP(Tabela2[[#This Row],[sigla]],créditos_base!B:C,2,0)) -> INGRIDHI BORGES/ARQUIVO DA EDITORA | Y8: Arte | Z8: =Tabela2[[#This Row],[ilustrador]] -> INGRIDHI BORGES/ARQUIVO DA EDITORA | AA8: 13 | AB8: PADRAO | AC8: FINALIZADO | AD8: ="Pitanguá" -> Pitanguá | AE8: ="Matemática" -> Matemática
A9: g0125_2p011m_g27_e001 | B9: APLICADA | C9: GRÁFICO | D9: MIOLO | F9: 2 | G9: 1 | H9: 1 | I9: AJUSTE | O9: Resgatar e ajustar gráfico sobre Filhotes que aparecem nas fotos, da página 134 do g23_mdn_lt_2npm_p128a135_u6; código antigo gt1206_2pmm_g19_mdn Ajuste: retirar barras em cor resposta | Q9: 13 | R9: 45743 | S9: 45743 | V9: 45743 | W9: sl | X9: =IF(Tabela2[[#This Row],[sigla]]="","",VLOOKUP(Tabela2[[#This Row],[sigla]],créditos_base!B:C,2,0)) -> SERGIO LIMA/ARQUIVO DA EDITORA | Y9: Tatiane Galheiro | Z9: =Tabela2[[#This Row],[ilustrador]] -> SERGIO LIMA/ARQUIVO DA EDITORA | AA9: 13 | AB9: Resgate com ajuste | AC9: FINALIZADO | AD9: ="Pitanguá" -> Pitanguá | AE9: ="Matemática" -> Matemática
A10: g0146_3p011m_g27_e001 | B10: APLICADA | C10: ILUSTRAÇÃO | D10: MIOLO | E10: 41 | F10: 3 | G10: 1 | I10: AJUSTE | O10: Resgatar gráfico/ilustração necessidade de horas de sono; g23_mdn_lt_3npm_p196; código antigo gt3409sl_3npm_g23_mdn_ef_aj AJUSTE: Retirar as barras em cor resposta | Q10: 78 | R10: 45820 | S10: 45825 | V10: 45826 | W10: sl | X10: =IF(Tabela2[[#This Row],[sigla]]="","",VLOOKUP(Tabela2[[#This Row],[sigla]],créditos_base!B:C,2,0)) -> SERGIO LIMA/ARQUIVO DA EDITORA | Y10: Rebecca Baniski | Z10: =Tabela2[[#This Row],[ilustrador]] -> SERGIO LIMA/ARQUIVO DA EDITORA | AA10: 13 | AB10: resgate com ajuste | AC10: FINALIZADO | AD10: ="Pitanguá" -> Pitanguá | AE10: ="Matemática" -> Matemática
A11: g0146_4p011m_g27_e001 | B11: APLICADA | C11: IL TEC ARTE | D11: MIOLO | E11: xx | F11: 4 | G11: 1 | I11: AJUSTE | O11: Resgatar gráfico de valores gastos e arrecadados. Veio de: g23_mdn_lt_4npm_p67 Código antigo: gt0806_4pmm_g19_mdn | Q11: 181 | R11: 45906 | S11: 45908 | V11: 45908 | W11: sl | X11: =IF(Tabela2[[#This Row],[sigla]]="","",VLOOKUP(Tabela2[[#This Row],[sigla]],créditos_base!B:C,2,0)) -> SERGIO LIMA/ARQUIVO DA EDITORA | Y11: Tamires Azevedo | Z11: =Tabela2[[#This Row],[ilustrador]] -> SERGIO LIMA/ARQUIVO DA EDITORA | AA11: 13 | AB11: ajuste de arte | AC11: FINALIZADO | AD11: ="Pitanguá" -> Pitanguá | AE11: ="Matemática" -> Matemática
A12: g0147_4p011m_g27_e001 | B12: EXCLUIDA | C12: IL TEC ARTE | D12: MIOLO | E12: xx | F12: 4 | G12: 1 | I12: RESGATE | O12: Resgatar gráfico de tempo por nome. Veio de: g23_mdn_lt_4npm_p068. Código antigo: gt0807_4pmm_g19_mdn | W12: sl | X12: =IF(Tabela2[[#This Row],[sigla]]="","",VLOOKUP(Tabela2[[#This Row],[sigla]],créditos_base!B:C,2,0)) -> SERGIO LIMA/ARQUIVO DA EDITORA | Z12: =Tabela2[[#This Row],[ilustrador]] -> SERGIO LIMA/ARQUIVO DA EDITORA | AD12: ="Pitanguá" -> Pitanguá | AE12: ="Matemática" -> Matemática
A13: g0148_4p011m_g27_e001 | B13: EXCLUIDA | C13: IL TEC ARTE | D13: MIOLO | E13: xx | F13: 4 | G13: 1 | I13: RESGATE | O13: Resgatar ilustração de um gráfico de barras tempo por nome. Veio de: g23_mdn_lt_4npm_p068. Código antigo: i1405ri_4npm_g23_mdn_aj | W13: ri | X13: =IF(Tabela2[[#This Row],[sigla]]="","",VLOOKUP(Tabela2[[#This Row],[sigla]],créditos_base!B:C,2,0)) -> RONALDO LUCENA/ARQUIVO DA EDITORA | Z13: =Tabela2[[#This Row],[ilustrador]] -> RONALDO LUCENA/ARQUIVO DA EDITORA | AD13: ="Pitanguá" -> Pitanguá | AE13: ="Matemática" -> Matemática
A14: g0151_3p011m_g27_e001 | B14: APLICADA | C14: ILUSTRAÇÃO | D14: MIOLO | E14: 47 | F14: 3 | G14: 1 | I14: AJUSTE | O14: Resgatar gráfico/ilustração quantidade de prefeitas eleitas por ano; g23_mdn_lt_3npm_p199; código antigo gt3411sl_3npm_g23_mdn_aj AJUSTE: O novo gráfico deve ir de 2004 a 2024 e representar os seguintes dados: 2004: 406 prefeitas eleitas 2008: 498 prefeitas eleitas 2012: 654 prefeitas eleitas 2016: 635 prefeitas eleitas 2020: 656 prefeitas eleitas 2024: 729 prefeitas eleitas Inserir fio contorno preto nas barras. | Q14: 78 | R14: 45820 | S14: 45828 | V14: 45831 | W14: sl | X14: =IF(Tabela2[[#This Row],[sigla]]="","",VLOOKUP(Tabela2[[#This Row],[sigla]],créditos_base!B:C,2,0)) -> SERGIO LIMA/ARQUIVO DA EDITORA | Y14: Ingridhi Borges | Z14: =Tabela2[[#This Row],[ilustrador]] -> SERGIO LIMA/ARQUIVO DA EDITORA | AA14: 13 | AB14: RESGATE COM AJUSTE | AC14: FINALIZADO | AD14: ="Pitanguá" -> Pitanguá | AE14: ="Matemática" -> Matemática
A15: g0153_4p011m_g27_e001 | B15: APLICADA | C15: GRÁFICO | D15: MIOLO | E15: 35 | F15: 4 | G15: 1 | I15: AJUSTE | O15: Resgatar e ajustar ilustração gráfico de barras verticais altitude de montanhas; g23_mdn_lt_4npm_p22; código antigo gt0217sl_4npm_g23_mdn_aj AJUSTE: O ajuste consiste em trocar "McKinley" por "Denali" e atualizar os dados das barras e alturas das barras conforme novo valor, com as seguintes informações: - Everest: 8 848 - Monte Branco: 4 808 - Denali: 6 194 - Pico da Neblina: 2 994 Além disso, mudar o nome do eixo vertical para "Medida da altitude (em metros)". | Q15: 91 | R15: 45840 | S15: 45849 | V15: 45850 | W15: sl | X15: =IF(Tabela2[[#This Row],[sigla]]="","",VLOOKUP(Tabela2[[#This Row],[sigla]],créditos_base!B:C,2,0)) -> SERGIO LIMA/ARQUIVO DA EDITORA | Y15: Maryane Vioto Silva | Z15: =Tabela2[[#This Row],[ilustrador]] -> SERGIO LIMA/ARQUIVO DA EDITORA | AA15: 14 | AB15: Resgate com ajuste | AC15: FINALIZADO | AD15: ="Pitanguá" -> Pitanguá | AE15: ="Matemática" -> Matemática
A16: g0160_2p011m_g27_e001 | B16: APLICADA | C16: GRÁFICO | D16: MIOLO | F16: 2 | G16: 1 | I16: AJUSTE | O16: Resgatar e ajustar gráfico com a Quantidade de bolinhas colocadas na caixa, da página 143 do g23_mdn_lt_2npm_p136a143_u6; código antigo gt2226km_2npm_g23_mdn AJUSTE 1: Ajustar o texto para CxAA e ajustar o gráfico para um gráfico na vertical. Além disso, após ajustar o gráfico na vertical, retirar os fios verticais e manter apenas os fios horizontais, ficando as barras por cima dos fios. AJUSTE 2: Ajustar também a cor das barras. Deixar uma única cor, diferente de roxo e azul. Aumentar também a quantidade de bolinhas correspondente a cor Roxa, devem ser 25 bolinhas. Se necessário, ajustar a escala do gráfico para fechar a página. | Q16: 52 | R16: 45803 | S16: 45805 | V16: 45805 | W16: km | X16: =IF(Tabela2[[#This Row],[sigla]]="","",VLOOKUP(Tabela2[[#This Row],[sigla]],créditos_base!B:C,2,0)) -> KEITHY MOSTACHI/ARQUIVO DA EDITORA | Y16: Vinícius Costa | Z16: =Tabela2[[#This Row],[ilustrador]] -> KEITHY MOSTACHI/ARQUIVO DA EDITORA | AA16: 14 | AB16: Resgate com ajuste | AC16: FINALIZADO | AD16: ="Pitanguá" -> Pitanguá | AE16: ="Matemática" -> Matemática
A17: g0161_2p011m_g27_e001 | B17: APLICADA | C17: GRÁFICO | D17: MIOLO | F17: 2 | G17: 1 | I17: AJUSTE | O17: Resgatar e ajustar gráfico sobre Quantidade de copos de suco vendidos no dia 15 de outubro de 2022, de acordo com o sabor, da página 135 do g23_mdn_lt_2npm_p128a135_u6; código antigo gt2218_2npm_g23_mdn_re. AJUSTE: Ajustar o texto do gráfico para que fique em CxAA. Além disso, retirar os fios horizontais do gráfico e não separar as barras em quadradinhos, ficando as barras por cima dos fios. | Q17: 52 | R17: 45803 | S17: 45805 | V17: 45805 | W17: sl | X17: =IF(Tabela2[[#This Row],[sigla]]="","",VLOOKUP(Tabela2[[#This Row],[sigla]],créditos_base!B:C,2,0)) -> SERGIO LIMA/ARQUIVO DA EDITORA | Y17: Vinícius Costa | Z17: =Tabela2[[#This Row],[ilustrador]] -> SERGIO LIMA/ARQUIVO DA EDITORA | AA17: 14 | AB17: Resgate com ajuste | AC17: FINALIZADO | AD17: ="Pitanguá" -> Pitanguá | AE17: ="Matemática" -> Matemática
A18: g0163_2p011m_g27_e001 | B18: APLICADA | C18: GRÁFICO | D18: MIOLO | F18: 2 | G18: 1 | I18: AJUSTE | O18: Resgatar e ajustar gráfico com a Quantidade de gols marcados por alguns jogadores do campeonato de futebol da escola, em 2022, da página 138 do g23_mdn_lt_2npm_p136a143_u6; código antigo gt1210_2pmm_g19_mdn. AJUSTE: Ajustar texto do gráfico em CxAA, e retirar as linhas para o estudante completar. No lugar delas entrará com nomes visíveis para o estudante. Na primeira coluna terá o nome "MÁRCIO.", na segunda "CAIO.", na terceira "JÚLIO." e na quarta "FABRÍCIO", conforme referência a seguir. | Q18: 52 | R18: 45803 | S18: 45805 | V18: 45805 | W18: sl | X18: =IF(Tabela2[[#This Row],[sigla]]="","",VLOOKUP(Tabela2[[#This Row],[sigla]],créditos_base!B:C,2,0)) -> SERGIO LIMA/ARQUIVO DA EDITORA | Y18: Vinícius Costa | Z18: =Tabela2[[#This Row],[ilustrador]] -> SERGIO LIMA/ARQUIVO DA EDITORA | AA18: 14 | AB18: Resgate com ajuste | AC18: FINALIZADO | AD18: ="Pitanguá" -> Pitanguá | AE18: ="Matemática" -> Matemática
A19: g0164_4p011m_g27_e001 | B19: APLICADA | C19: GRÁFICO | D19: MIOLO | E19: 30 | F19: 4 | G19: 1 | I19: NOVA | O19: Ilustração de um pictograma para representar os dados do quadro a seguir. Tipo de animal Quantidade de razão (em kg) Búfalo 1 700 Porco 1 300 Galinha 1 100 O elemento pictórico deve ser sacas de ração. Nesse pictograma, cada saca deve representar 100 kg. Assim, na barra dos búfalos devem aparecer 17 sacas, dos porcos, 13, e das galinhas, 11. | Q19: 91 | R19: 45840 | S19: 45849 | V19: 45853 | W19: rm | X19: =IF(Tabela2[[#This Row],[sigla]]="","",VLOOKUP(Tabela2[[#This Row],[sigla]],créditos_base!B:C,2,0)) -> HELOÍSA PINTARELLI/ARQUIVO DA EDITORA | Z19: =Tabela2[[#This Row],[ilustrador]] -> HELOÍSA PINTARELLI/ARQUIVO DA EDITORA | AA19: 11 | AB19: FINALIZADA 16/07 | AC19: PAGO | AD19: ="Pitanguá" -> Pitanguá | AE19: ="Matemática" -> Matemática
A20: g0189_3p011m_g27_e001 | B20: APLICADA | C20: ILUSTRAÇÃO | D20: MIOLO | E20: 43 | F20: 3 | G20: 1 | I20: NOVA | O20: ilustração de gráfico de barras verticais com o eixo horizontal “Município” e o eixo vertical “Quantidade de pessoas. Esse gráfico de barras terá os seguintes dados: Altônia: 720 pessoas; Barbosa Ferraz: 462 pessoas; Carambeí: 770 pessoas; Engenheiro Beltrão: 641 pessoas; Iporã: 970 pessoas; Loanda: 766 pessoas. | Q20: 78 | R20: 45820 | S20: 45825 | V20: 45826 | W20: bk | X20: =IF(Tabela2[[#This Row],[sigla]]="","",VLOOKUP(Tabela2[[#This Row],[sigla]],créditos_base!B:C,2,0)) -> REBECCA BANISKI/ARQUIVO DA EDITORA | Z20: =Tabela2[[#This Row],[ilustrador]] -> REBECCA BANISKI/ARQUIVO DA EDITORA | AA20: 12 | AB20: Arte | AC20: FINALIZADO | AD20: ="Pitanguá" -> Pitanguá | AE20: ="Matemática" -> Matemática
A21: g0327_1p011m_g27_e001 | B21: APLICADA | C21: GRÁFICO | D21: MIOLO | E21: 52 | F21: 1 | G21: 2 | I21: NOVA | O21: Il. de gráfico de barras verticais com os eixos “QUANTIDADE DE CACHORROS” e “FOTO”. No eixo horizontal deve estar a indicação para cada coluna: FOTO 1; FOTO 2; FOTO 3; FOTO 4. Cada coluna deve ter uma barra com 7 quadradinhos cada. ARTE: usar a base da il gt4022sl_1bam_g23_ftd pegar essa só de exemplo para compor o gráfico, deixar os espaços mais quadradinhos e não tão retangulares, fazer conforme a referência. | Q21: 8 | R21: 45733 | S21: 45734 | V21: 45734 | W21: fg | X21: =IF(Tabela2[[#This Row],[sigla]]="","",VLOOKUP(Tabela2[[#This Row],[sigla]],créditos_base!B:C,2,0)) -> FELIPE GRIGOLI/ARQUIVO DA EDITORA | Y21: Arte | Z21: =Tabela2[[#This Row],[ilustrador]] -> FELIPE GRIGOLI/ARQUIVO DA EDITORA | AA21: 12 | AB21: PADRÃO | AC21: FINALIZADO | AD21: ="Pitanguá" -> Pitanguá | AE21: ="Matemática" -> Matemática
A22: g0508_5p011m_g27_e001 | B22: APLICADA | C22: GRÁFICO | D22: MIOLO | E22: 52 | F22: 5 | G22: 3 | I22: AJUSTE | O22: Resgatar gráfico do esporte preferido de estudantes da página 100 do g23_mdn_lt_5npm_p096a103_u5. Código antigo gt1005_5pmm_g19_mdn AJUSTE 1: Trocar nome do eixo "Quantidade de alunos" para "Quantidade de estudantes". AJUSTE 2: Além disso, tirar as linhas horizontais e verticais do gráfico, ou seja, deixá-lo com o fundo branco. | Q22: 55 | R22: 45803 | S22: 45810 | V22: 45810 | W22: ri | X22: =IF(Tabela2[[#This Row],[sigla]]="","",VLOOKUP(Tabela2[[#This Row],[sigla]],créditos_base!B:C,2,0)) -> RONALDO LUCENA/ARQUIVO DA EDITORA | Y22: Rebecca Baniski | Z22: =Tabela2[[#This Row],[ilustrador]] -> RONALDO LUCENA/ARQUIVO DA EDITORA | AB22: resgate com ajuste | AC22: FINALIZADO | AD22: ="Pitanguá" -> Pitanguá | AE22: ="Matemática" -> Matemática
A23: g0509_5p011m_g27_e001 | B23: APLICADA | C23: GRÁFICO | D23: MIOLO | E23: 54 | F23: 5 | G23: 3 | I23: AJUSTE | O23: Resgatar gráfico da quantidade de meninos e meninas, escrita em letras cursivas da página 102 do g23_mdn_lt_5npm_p096a103_u5. Código antigo gt1805ri_5npm_g23_mdn_aj. AJUSTE: atualizar ano para 2027 | Q23: 55 | R23: 45803 | S23: 45810 | V23: 45810 | W23: ri | X23: =IF(Tabela2[[#This Row],[sigla]]="","",VLOOKUP(Tabela2[[#This Row],[sigla]],créditos_base!B:C,2,0)) -> RONALDO LUCENA/ARQUIVO DA EDITORA | Y23: Rebecca Baniski | Z23: =Tabela2[[#This Row],[ilustrador]] -> RONALDO LUCENA/ARQUIVO DA EDITORA | AB23: resgate com ajuste | AC23: FINALIZADO | AD23: ="Pitanguá" -> Pitanguá | AE23: ="Matemática" -> Matemática
A24: g0511_5p011m_g27_e001 | B24: APLICADA | C24: GRÁFICO | D24: MIOLO | E24: 58 | F24: 5 | G24: 3 | I24: RESGATE | O24: Resgatar gráfico/pictograma de preferência de sabor de suco da página 104 do g23_mdn_lt_5npm_p104a111_u5. Código antigo gt1807ri_5npm_g23_mdn_aj | W24: ri | X24: =IF(Tabela2[[#This Row],[sigla]]="","",VLOOKUP(Tabela2[[#This Row],[sigla]],créditos_base!B:C,2,0)) -> RONALDO LUCENA/ARQUIVO DA EDITORA | Z24: =Tabela2[[#This Row],[ilustrador]] -> RONALDO LUCENA/ARQUIVO DA EDITORA | AD24: ="Pitanguá" -> Pitanguá | AE24: ="Matemática" -> Matemática
A25: g0512_5p011m_g27_e001 | B25: APLICADA | C25: GRÁFICO | D25: MIOLO | E25: 59 | F25: 5 | G25: 3 | I25: AJUSTE | O25: Resgatar gráfico de medalhas conquistadas por alguns países da página 105 do g23_mdn_lt_5npm_p104a111_u5. Código antigo gt1009_5pmm_g19_mdn AJUSTE 1: retirar textos em cor resposta AJUSTE 2: Ajustar tamanho das barras e atualizar os valores. De cima para baixo, as barras devem indicar, respectivamente, 53, 20, 91, 126, 32, 64, 40, 11. | Q25: 55 | R25: 45803 | S25: 45810 | V25: 45810 | W25: ri | X25: =IF(Tabela2[[#This Row],[sigla]]="","",VLOOKUP(Tabela2[[#This Row],[sigla]],créditos_base!B:C,2,0)) -> RONALDO LUCENA/ARQUIVO DA EDITORA | Y25: Rebecca Baniski | Z25: =Tabela2[[#This Row],[ilustrador]] -> RONALDO LUCENA/ARQUIVO DA EDITORA | AB25: resgate com ajuste | AC25: FINALIZADO | AD25: ="Pitanguá" -> Pitanguá | AE25: ="Matemática" -> Matemática
A26: g0513_5p011m_g27_e001 | B26: APLICADA | C26: GRÁFICO | D26: MIOLO | E26: 60 | F26: 5 | G26: 3 | I26: AJUSTE | O26: Resgatar o gráfico de despesa mensal com energia elétrica da página 106 do g23_mdn_lt_5npm_p104a111_u5. Código antigo gt1036_5pmm_g19_mdn | Q26: 200 | R26: 45923 | S26: 45923 | V26: 45923 | W26: sl | X26: =IF(Tabela2[[#This Row],[sigla]]="","",VLOOKUP(Tabela2[[#This Row],[sigla]],créditos_base!B:C,2,0)) -> SERGIO LIMA/ARQUIVO DA EDITORA | Y26: Vinícius Costa | Z26: =Tabela2[[#This Row],[ilustrador]] -> SERGIO LIMA/ARQUIVO DA EDITORA | AA26: 13 | AC26: FINALIZADO | AD26: ="Pitanguá" -> Pitanguá | AE26: ="Matemática" -> Matemática
A27: g0522_4p011m_g27_e001 | B27: APLICADA | C27: GRÁFICO | D27: MIOLO | E27: 67 | F27: 4 | G27: 3 | I27: AJUSTE | O27: Resgatar gráfico de dispositivo mais usado. Veio de: g23_mdn_lt_4npm_p073. Código antigo: gt1411ri_4npm_g23_mdn_aj AJUSTE: Mudar nome do eixo vertical, deve ser: Quantidade de estudantes e ajustar valores (consequentemente a escala do eixo vertical). Os novos valores são: Smartphone: 1 190 Tablet: 1 075 Notebook: 1 125 Computador de mesa: 1 110 | Q27: 97 | R27: 45845 | S27: 45852 | V27: 45861 | W27: ri | X27: =IF(Tabela2[[#This Row],[sigla]]="","",VLOOKUP(Tabela2[[#This Row],[sigla]],créditos_base!B:C,2,0)) -> RONALDO LUCENA/ARQUIVO DA EDITORA | Y27: Maryane Vioto Silva | Z27: =Tabela2[[#This Row],[ilustrador]] -> RONALDO LUCENA/ARQUIVO DA EDITORA | AA27: 13 | AB27: Resgate com ajuste | AC27: FINALIZADO | AD27: ="Pitanguá" -> Pitanguá | AE27: ="Matemática" -> Matemática
A28: g0523_5p011m_g27_e001 | B28: APLICADA | C28: GRÁFICO | D28: MIOLO | E28: 72 | F28: 5 | G28: 3 | I28: AJUSTE | O28: Resgatar gráfico/ilustração quantidade de estudantes de cinco turmas da escola; g23_mdn_lt_5npm_p54. Código antigo: gt0619_5pmm_g19_mdn AJUSTE: Trocar "Quantidade de alunos" por "Quantidade de estudantes". Compor fio preto em torno da barras de acordo com padrão. | Q28: 135 | R28: 45866 | S28: 45877 | V28: 45877 | W28: ri | X28: =IF(Tabela2[[#This Row],[sigla]]="","",VLOOKUP(Tabela2[[#This Row],[sigla]],créditos_base!B:C,2,0)) -> RONALDO LUCENA/ARQUIVO DA EDITORA | Y28: Gabriella Imai | Z28: =Tabela2[[#This Row],[ilustrador]] -> RONALDO LUCENA/ARQUIVO DA EDITORA | AA28: 13 | AB28: resgate com ajuste | AC28: FINALIZADO | AD28: ="Pitanguá" -> Pitanguá | AE28: ="Matemática" -> Matemática
A29: g0529_5p011m_g27_e001 | B29: APLICADA | C29: GRÁFICO | D29: MIOLO | E29: 56 | F29: 5 | G29: 3 | I29: NOVA | O29: Compor gráfico de colunas verticais para representar os dados do quadro a seguir. Frutas Quantidade de colegas Maçã 8 Banana 13 Laranja 9 Melancia 6 Kiwi 3 Além disso, compor título e fonte de pesquisa. São eles: Título: “Fruta preferida pelos colegas de Fabrício, em 18 de março de 2026”; Fonte de pesquisa: “Fonte de pesquisa: Anotações de Fabrício”. OBS: TODAS as informações que aparecem nessa il. devem ser feitas manuscritas e em letra cursiva. O gráfico deve ser ilustrado como se tivesse sido feito por uma pessoa. | Q29: 135 | R29: 45866 | S29: 45874 | V29: 45877 | W29: rm | X29: =IF(Tabela2[[#This Row],[sigla]]="","",VLOOKUP(Tabela2[[#This Row],[sigla]],créditos_base!B:C,2,0)) -> HELOÍSA PINTARELLI/ARQUIVO DA EDITORA | Z29: =Tabela2[[#This Row],[ilustrador]] -> HELOÍSA PINTARELLI/ARQUIVO DA EDITORA | AA29: 11 | AB29: FINALIZADA: 07/08 | AC29: PAGO | AD29: ="Pitanguá" -> Pitanguá | AE29: ="Matemática" -> Matemática
A30: g0531_2p011m_g27_e001 | B30: APLICADA | C30: GRÁFICO | D30: MIOLO | E30: 92 | F30: 2 | G30: 3 | I30: AJUSTE | O30: Resgatar gráfico sobre Brinquedos vendidos no dia 4 de julho de 2022, da página 133 do g23_mdn_lt_2npm_p128a135_u6; código antigo gt2217_2npm_g23_mdn_re AJUSTE: inserir até o número 13 no eixo “Quantidade vendida” e ajustar o gráfico para 10 bolas de futebol, 5 bonecas, 12 pipas e 4 ursos de pelúcia e deixar todo o texto em caixa alta alta. | Q30: 64 | R30: 45810 | S30: 45811 | V30: 45811 | W30: sl | X30: =IF(Tabela2[[#This Row],[sigla]]="","",VLOOKUP(Tabela2[[#This Row],[sigla]],créditos_base!B:C,2,0)) -> SERGIO LIMA/ARQUIVO DA EDITORA | Y30: Tamires Azevedo | Z30: =Tabela2[[#This Row],[ilustrador]] -> SERGIO LIMA/ARQUIVO DA EDITORA | AA30: 13 | AB30: Ajuste de arte | AC30: FINALIZADO | AD30: ="Pitanguá" -> Pitanguá | AE30: ="Matemática" -> Matemática
A31: g0532_4p011m_g27_e001 | B31: PRONTA | C31: GRÁFICO | D31: MIOLO | E31: xx | F31: 4 | G31: 2 | I31: RESGATE | O31: Resgatar ilustração de gráfico de quantidade de picolés. Veio de: g23_mdn_lt_4npm_p065. Código antigo: i1403ri_4npm_g23_mdn_aj | W31: ri | X31: =IF(Tabela2[[#This Row],[sigla]]="","",VLOOKUP(Tabela2[[#This Row],[sigla]],créditos_base!B:C,2,0)) -> RONALDO LUCENA/ARQUIVO DA EDITORA | Z31: =Tabela2[[#This Row],[ilustrador]] -> RONALDO LUCENA/ARQUIVO DA EDITORA | AD31: ="Pitanguá" -> Pitanguá | AE31: ="Matemática" -> Matemática
A32: g0534_4p011m_g27_e001 | B32: PRONTA | C32: GRÁFICO | D32: MIOLO | E32: xx | F32: 4 | G32: 2 | I32: RESGATE | O32: Resgatar gráfico de público do cinema. Veio de: g23_mdn_lt_4npm_p075. Código antigo: gt2501_4npm_m20_mdn | X32: =IF(Tabela2[[#This Row],[sigla]]="","",VLOOKUP(Tabela2[[#This Row],[sigla]],créditos_base!B:C,2,0)) | Z32: =Tabela2[[#This Row],[ilustrador]] | AD32: ="Pitanguá" -> Pitanguá | AE32: ="Matemática" -> Matemática
A33: g0535_3p011m_g27_e001 | B33: EXCLUIDA | C33: GRÁFICO | D33: MIOLO | E33: 195 | F33: 3 | G33: 3 | I33: RESGATE | O33: Resgatar ilustração gráfico pesquisa dos estudantes aniversários; g23_mdn_lt_3npm_p195; código antigo gt3414sl_3npm_g23_mdn_aj | P33: Excluída pela equipe. | W33: sl | X33: =IF(Tabela2[[#This Row],[sigla]]="","",VLOOKUP(Tabela2[[#This Row],[sigla]],créditos_base!B:C,2,0)) -> SERGIO LIMA/ARQUIVO DA EDITORA | Z33: =Tabela2[[#This Row],[ilustrador]] -> SERGIO LIMA/ARQUIVO DA EDITORA | AD33: ="Pitanguá" -> Pitanguá | AE33: ="Matemática" -> Matemática
A34: g0554_3p011m_g27_e001 | B34: APLICADA | C34: GRÁFICO | D34: MIOLO | E34: 91 | F34: 3 | G34: 3 | I34: NOVA | O34: Ilustração de um gráfico de barras horizontais no padrão da obra. Esse gráfico deve representar as informações do quadro a seguir. Fazer nesse padrão, porém sendo barras horizontais. | Q34: 43 | R34: 45790 | S34: 45790 | V34: 45791 | W34: rm | X34: =IF(Tabela2[[#This Row],[sigla]]="","",VLOOKUP(Tabela2[[#This Row],[sigla]],créditos_base!B:C,2,0)) -> HELOÍSA PINTARELLI/ARQUIVO DA EDITORA | Z34: =Tabela2[[#This Row],[ilustrador]] -> HELOÍSA PINTARELLI/ARQUIVO DA EDITORA | AA34: 12 | AB34: F: 15/05 | AC34: PAGO | AD34: ="Pitanguá" -> Pitanguá | AE34: ="Matemática" -> Matemática
A35: g0555_4p011m_g27_e001 | B35: APLICADA | C35: GRÁFICO | D35: MIOLO | E35: 62 | F35: 4 | G35: 3 | I35: NOVA | O35: Compor gráfico de barras verticais para representar os dados do quadro a seguir. Posto de coleta Quantidade (em quilogramas) A 1 210 B 1 190 C 1 260 D 1 120 No gráfico, A, B, C e D devem estar em bold. | Q35: 97 | R35: 45845 | S35: 45852 | V35: 45861 | W35: mv | X35: =IF(Tabela2[[#This Row],[sigla]]="","",VLOOKUP(Tabela2[[#This Row],[sigla]],créditos_base!B:C,2,0)) -> MARYANE VIOTO SILVA/ARQUIVO DA EDITORA | Z35: =Tabela2[[#This Row],[ilustrador]] -> MARYANE VIOTO SILVA/ARQUIVO DA EDITORA | AA35: 12 | AB35: Arte | AC35: FINALIZADO | AD35: ="Pitanguá" -> Pitanguá | AE35: ="Matemática" -> Matemática
A36: g0716_3p011m_g27_e001 | B36: APLICADA | C36: GRÁFICO | D36: MIOLO | E36: 105 | F36: 3 | G36: 4 | I36: AJUSTE | O36: Resgatar e ajustar gráfico sobre pesquisa sobre o uso do computador no dia a dia dos estudantes, da página 69 do g23_mdn_lt_3npm_p064a069_u3. Código antigo i0621rm_3pmm_g19_mdn AJUSTE: Adicionar eixo faltante (horizontal) e os nomes do eixo. O nome do eixo horizontal será "Quantidade de estudantes" e o eixo vertical será "Frequência de uso" AJUSTE: inserir eixo horizontal e os nomes do eixo. O nome do eixo horizontal será "Quantidade de estudantes" e o eixo vertical será "Frequência de uso". No eixo horizontal, deixar a escala de 3 em 3. Aproximar os bonequinhos do eixo vertical e retirar o fundo cor que está embaixo dos bonequinhos. Ver referência a seguir. | Q36: 48 | R36: 45797 | S36: 45797 | V36: 45798 | W36: rm | X36: =IF(Tabela2[[#This Row],[sigla]]="","",VLOOKUP(Tabela2[[#This Row],[sigla]],créditos_base!B:C,2,0)) -> HELOÍSA PINTARELLI/ARQUIVO DA EDITORA | Y36: Bruna Campos | Z36: =Tabela2[[#This Row],[ilustrador]] -> HELOÍSA PINTARELLI/ARQUIVO DA EDITORA | AA36: 13 | AB36: Resgate com ajuste | AC36: FINALIZADO | AD36: ="Pitanguá" -> Pitanguá | AE36: ="Matemática" -> Matemática
A37: g0725_1p011m_g27_e001 | B37: APLICADA | C37: GRÁFICO | D37: MIOLO | E37: 113 | F37: 1 | G37: 4 | I37: NOVA | O37: Ilustração de gráfico de barras com eixo vertical “FRUTA” e eixo horizontal “MEDIDA DE MASSA (EM QUILOGRAMAS)”. No eixo “FRUTA” é composto pelas frutas “PÊSSEGO”, “LARANJA”, “MELANCIA”, “MAÇÃ” e BANANA. A barra em frente de cada fruta será dividida em 10 quadrados iguais, conforme a referência. Pode usar como base a gt3032_1npm_g23_mdn_aj, adaptando de acordo com a descrição acima. Deixar as barras em branco para o aluno pintar. | Q37: 30 | R37: 45755 | S37: 45756 | V37: 45756 | W37: km | X37: =IF(Tabela2[[#This Row],[sigla]]="","",VLOOKUP(Tabela2[[#This Row],[sigla]],créditos_base!B:C,2,0)) -> KEITHY MOSTACHI/ARQUIVO DA EDITORA | Y37: Arte | Z37: =Tabela2[[#This Row],[ilustrador]] -> KEITHY MOSTACHI/ARQUIVO DA EDITORA | AA37: 12 | AB37: padrão | AC37: FINALIZADO | AD37: ="Pitanguá" -> Pitanguá | AE37: ="Matemática" -> Matemática
A38: g0728_1p011m_g27_e001 | B38: PRONTA | C38: GRÁFICO | D38: MIOLO | E38: 118 | F38: 1 | G38: 4 | I38: NOVA | O38: Ilustração de um gráfico de barras (vertical) no padrão da obra que apresente os dados do quadro a seguir. Fazer com base no gt1228_1npm_m20_mdn_re, adaptando conforme a referência a seguir. Ver se é preciso aproximar as barras. O eixo vertical, pode ficar até o 7. SABOR MEDIDA DA CAPACIDADE (EM LITROS) LARANJA 4 UVA 5 ACEROLA 2 MARACUJÁ 2 | Q38: 30 | R38: 45755 | S38: 45756 | V38: 45756 | W38: km | X38: =IF(Tabela2[[#This Row],[sigla]]="","",VLOOKUP(Tabela2[[#This Row],[sigla]],créditos_base!B:C,2,0)) -> KEITHY MOSTACHI/ARQUIVO DA EDITORA | Y38: Arte | Z38: =Tabela2[[#This Row],[ilustrador]] -> KEITHY MOSTACHI/ARQUIVO DA EDITORA | AA38: 12 | AB38: padrão | AC38: FINALIZADO | AD38: ="Pitanguá" -> Pitanguá | AE38: ="Matemática" -> Matemática
A39: g0728_3p011m_g27_e001 | B39: APLICADA | C39: GRÁFICO | D39: MIOLO | E39: 77 | F39: 3 | G39: 4 | I39: AJUSTE | O39: Resgatar e ajustar gráfico de quantidade de livros vendidos. Veio de: g23_mdn_lt_3npm_p077.Ccódigo antigo: gt1037zz_3npm_g23_mdn_aj AJUSTE: compor fio contorno preto do padrão da obra em torno das barras do gráfico. | Q39: 81 | R39: 45824 | V39: 45824 | W39: sl | X39: =IF(Tabela2[[#This Row],[sigla]]="","",VLOOKUP(Tabela2[[#This Row],[sigla]],créditos_base!B:C,2,0)) -> SERGIO LIMA/ARQUIVO DA EDITORA | Y39: Rebecca Baniski | Z39: =Tabela2[[#This Row],[ilustrador]] -> SERGIO LIMA/ARQUIVO DA EDITORA | AA39: 13 | AB39: resgate ajuste | AC39: FINALIZADO | AD39: ="Pitanguá" -> Pitanguá | AE39: ="Matemática" -> Matemática
A40: g0731_3p011m_g27_e001 | B40: APLICADA | C40: GRÁFICO | D40: MIOLO | E40: 193 | F40: 3 | G40: 4 | I40: AJUSTE | O40: Resgatar gráfico/ilustração quantidade de estudantes; g23_mdn_lt_3npm_p193; código antigo gt1806_3pmm_g19_mdn AJUSTE: retirar barras em cor resposta | Q40: 26 | R40: 45751 | S40: 45751 | V40: 45751 | W40: sl | X40: =IF(Tabela2[[#This Row],[sigla]]="","",VLOOKUP(Tabela2[[#This Row],[sigla]],créditos_base!B:C,2,0)) -> SERGIO LIMA/ARQUIVO DA EDITORA | Y40: Rafaela Panissa | Z40: =Tabela2[[#This Row],[ilustrador]] -> SERGIO LIMA/ARQUIVO DA EDITORA | AA40: 14 | AB40: resgate ajuste | AC40: FINALIZADO | AD40: ="Pitanguá" -> Pitanguá | AE40: ="Matemática" -> Matemática
A41: g0789_5p011m_g27_e001 | B41: APLICADA | C41: IL TEC ARTE | D41: MIOLO | E41: 115 | F41: 5 | G41: 4 | I41: AJUSTE | O41: Resgatar ilustração de um gráfico de setores de consumo de energia elétrica. Veio de: g23_mdn_lt_5npm_p094. Código antigo: gt1419ri_5npm_g23_mdn_aj AJUSTE 1: atualizar dados para as seguintes informações: Residências: \frac{31}{100}; Indústrias: \frac{7}{20}; Comércio: \frac{19}{100}; Outros: \frac{3}{20} AJUSTE 2: compor fio preto em torno dos setores conforme padrão. | Q41: 136 | R41: 45866 | S41: 45875 | V41: 45877 | W41: ri | X41: =IF(Tabela2[[#This Row],[sigla]]="","",VLOOKUP(Tabela2[[#This Row],[sigla]],créditos_base!B:C,2,0)) -> RONALDO LUCENA/ARQUIVO DA EDITORA | Y41: Arte | Z41: =Tabela2[[#This Row],[ilustrador]] -> RONALDO LUCENA/ARQUIVO DA EDITORA | AA41: 12 | AB41: ARTE | AC41: FINALIZADO | AD41: ="Pitanguá" -> Pitanguá | AE41: ="Matemática" -> Matemática
A42: g0931_2p011m_g27_e001 | B42: APLICADA | C42: ILUSTRAÇÃO | D42: MIOLO | E42: 75 | F42: 2 | G42: 5 | I42: AJUSTE | O42: Resgatar grafico de barras, na página 75 do g23_mdn_lt_2npm_p070a078_u3; código antigo gt1005sl_2npm_g23_mdn_aj AJUSTE: retirar barras em cor resposta | Q42: 17 | R42: 45747 | S42: 45747 | V42: 45747 | W42: sl | X42: =IF(Tabela2[[#This Row],[sigla]]="","",VLOOKUP(Tabela2[[#This Row],[sigla]],créditos_base!B:C,2,0)) -> SERGIO LIMA/ARQUIVO DA EDITORA | Y42: Keithy Mostachi | Z42: =Tabela2[[#This Row],[ilustrador]] -> SERGIO LIMA/ARQUIVO DA EDITORA | AA42: 13 | AB42: resgate ajuste | AC42: FINALIZADO | AD42: ="Pitanguá" -> Pitanguá | AE42: ="Matemática" -> Matemática
A43: g0946_4p011m_g27_e001 | B43: APLICADA | C43: ILUSTRAÇÃO | D43: MIOLO | E43: 146 | F43: 4 | G43: 5 | I43: AJUSTE | O43: Resgatar ilustração de um gráfico de barras; disponível em; g23_mdn_lt_4npm_p128_u6 codigo gt1415_4pmm_g19_mdn | Q43: 107 | R43: 45850 | S43: 45853 | V43: 45856 | W43: sl | X43: =IF(Tabela2[[#This Row],[sigla]]="","",VLOOKUP(Tabela2[[#This Row],[sigla]],créditos_base!B:C,2,0)) -> SERGIO LIMA/ARQUIVO DA EDITORA | Y43: Arte | Z43: =Tabela2[[#This Row],[ilustrador]] -> SERGIO LIMA/ARQUIVO DA EDITORA | AA43: 13 | AB43: RESGATE COM AJUSTE | AC43: FINALIZADO | AD43: ="Pitanguá" -> Pitanguá | AE43: ="Matemática" -> Matemática
A44: g1112_2p011m_g27_e001 | B44: APLICADA | C44: IL TEC ARTE | D44: MIOLO | E44: 155 | F44: 2 | G44: 6 | I44: NOVA | O44: Ilustração de um gráfico de barras verticais com o eixo vertical “Quantidade de habitantes” e o eixo horizontal “Municípios”. O gráfico terá um escala de 200, começando do 0 até o 1 200. Esse gráfico deve apresentar os seguintes dados: Serra da Saudade: 854; Anhanguera: 921; Borá: 928. Esses valores devem estar apresentados acima das barras verticais. Utilizar como referência o gt1411ri_2npm_g23_mdn_aj (enviado na pasta) | Q44: 71 | R44: 45813 | S44: 45814 | V44: 45818 | W44: bk | X44: =IF(Tabela2[[#This Row],[sigla]]="","",VLOOKUP(Tabela2[[#This Row],[sigla]],créditos_base!B:C,2,0)) -> REBECCA BANISKI/ARQUIVO DA EDITORA | Z44: =Tabela2[[#This Row],[ilustrador]] -> REBECCA BANISKI/ARQUIVO DA EDITORA | AA44: 12 | AB44: arte | AC44: FINALIZADO | AD44: ="Pitanguá" -> Pitanguá | AE44: ="Matemática" -> Matemática
A45: g1126_3p011m_g27_e001 | B45: APLICADA | C45: GRÁFICO | D45: MIOLO | E45: 110 | F45: 3 | G45: 6 | I45: AJUSTE | O45: Resgatar ilustração/gráfico das alturas de quatro crianças; g23_mdn_lt_3npm_p110; código antigo g1819rl_3npm_g23_mdn_aj | Q45: 127 | R45: 45862 | S45: 45863 | V45: 45863 | W45: rl | X45: =IF(Tabela2[[#This Row],[sigla]]="","",VLOOKUP(Tabela2[[#This Row],[sigla]],créditos_base!B:C,2,0)) -> RAFAEL LAM/ARQUIVO DA EDITORA | Y45: Arte | Z45: =Tabela2[[#This Row],[ilustrador]] -> RAFAEL LAM/ARQUIVO DA EDITORA | AA45: 13 | AB45: RESGATE COM AJUSTE | AC45: FINALIZADO | AD45: ="Pitanguá" -> Pitanguá | AE45: ="Matemática" -> Matemática
A46: g1134_5p011m_g27_e001 | B46: APLICADA | C46: GRÁFICO | D46: MIOLO | E46: 123 | F46: 5 | G46: 6 | I46: AJUSTE | O46: Resgatar gráfico de barras da quantia de energia gasta da página 123 do g23_mdn_lt_5npm_p120a123_u6. Código antigo: gt2223ri_5npm_g23_mdn_aj AJUSTE: inserir fio preto envolta das colunas conforme padrão. Retirar cor resposta. Ajustar gráfico para os seguintes dados: - Televisor: 5,04; - Geladeira: 6,30; - Computador: 7,56; - Ferro-elétrico: 25,20 - Chuveiro: 151,20.. | Q46: 77 | R46: 45819 | S46: 45866 | V46: 45868 | W46: ri | X46: =IF(Tabela2[[#This Row],[sigla]]="","",VLOOKUP(Tabela2[[#This Row],[sigla]],créditos_base!B:C,2,0)) -> RONALDO LUCENA/ARQUIVO DA EDITORA | Y46: Maryane Vioto SIlva | Z46: =Tabela2[[#This Row],[ilustrador]] -> RONALDO LUCENA/ARQUIVO DA EDITORA | AA46: 14 | AB46: Resgate com ajuste | AC46: FINALIZADO | AD46: ="Pitanguá" -> Pitanguá | AE46: ="Matemática" -> Matemática
A47: g1141_5p011m_g27_e001 | B47: APLICADA | C47: GRÁFICO | D47: MIOLO | E47: 127 | F47: 5 | G47: 6 | I47: AJUSTE | O47: Resgatar gráfico do aumento de massa da página 127 do g23_mdn_lt_5npm_p124a127_u6. Código antigo: gt2224ri_5npm_g23_mdn_aj AJUSTE: inserir fio preto envolta das colunas conforme padrão. | Q47: 77 | R47: 45819 | S47: 45866 | V47: 45868 | W47: ri | X47: =IF(Tabela2[[#This Row],[sigla]]="","",VLOOKUP(Tabela2[[#This Row],[sigla]],créditos_base!B:C,2,0)) -> RONALDO LUCENA/ARQUIVO DA EDITORA | Y47: Maryane Vioto SIlva | Z47: =Tabela2[[#This Row],[ilustrador]] -> RONALDO LUCENA/ARQUIVO DA EDITORA | AA47: 14 | AB47: Resgate com ajuste | AC47: FINALIZADO | AD47: ="Pitanguá" -> Pitanguá | AE47: ="Matemática" -> Matemática
A48: g1163_5p011m_g27_e001 | B48: APLICADA | C48: GRÁFICO | D48: MIOLO | E48: 173 | F48: 5 | G48: 6 | I48: NOVA | O48: Compor gráfico de barras verticais para representar os dados do quadro a seguir. O eixo vertical pode ser dividido de 0,4 em 0,4 até 2,4. Ano Quantidade (em milhões) 2016 2,112 2022 1,881 2023 1,607 | Q48: 139 | R48: 45868 | S48: 45868 | V48: 45874 | W48: vc | X48: =IF(Tabela2[[#This Row],[sigla]]="","",VLOOKUP(Tabela2[[#This Row],[sigla]],créditos_base!B:C,2,0)) -> VINÍCIUS COSTA/ARQUIVO DA EDITORA | Z48: =Tabela2[[#This Row],[ilustrador]] -> VINÍCIUS COSTA/ARQUIVO DA EDITORA | AA48: 12 | AB48: Arte | AC48: FINALIZADO | AD48: ="Pitanguá" -> Pitanguá | AE48: ="Matemática" -> Matemática
A49: g1185_1p011m_g27_e001 | B49: APLICADA | C49: GRÁFICO | D49: MIOLO | E49: 140 | F49: 1 | G49: 6 | I49: AJUSTE | O49: Resgatar ilustração de gráfico de barras sobre quantidade de figurinhas dos amigos de José, em g23_mdn_lt_1npm_p0140_u6, código gt1230_1pmm_g19_mdn. AJUSTE: Mantendo a mesma escala de 1 em 1, aumentar o eixo vertical até 15. Além disso, ajsutar os valores de cada barra com as seguintes informações: CAIO: 15 FÁTIMA: 13 CRISTIANO: 11 BRENO: 8 BRUNA: 11 | Q49: 35 | R49: 45771 | S49: 45775 | V49: 45777 | W49: sl | X49: =IF(Tabela2[[#This Row],[sigla]]="","",VLOOKUP(Tabela2[[#This Row],[sigla]],créditos_base!B:C,2,0)) -> SERGIO LIMA/ARQUIVO DA EDITORA | Y49: Vinícius Costa | Z49: =Tabela2[[#This Row],[ilustrador]] -> SERGIO LIMA/ARQUIVO DA EDITORA | AA49: 13 | AB49: Resgate com ajuste | AC49: FINALIZADO | AD49: ="Pitanguá" -> Pitanguá | AE49: ="Matemática" -> Matemática
A50: g1188_1p011m_g27_e001 | B50: APLICADA | C50: GRÁFICO | D50: MIOLO | E50: 160 | F50: 1 | G50: 6 | I50: RESGATE | O50: g1188_1p011m_g27_e001 RESGATE Resgatar ilustração de um gráfico de barras sobre brincadeita favorita, em g23_mdn_lt_1npm_p0141_u6, código gt1232_1pmm_g19_mdn. | W50: sl | X50: =IF(Tabela2[[#This Row],[sigla]]="","",VLOOKUP(Tabela2[[#This Row],[sigla]],créditos_base!B:C,2,0)) -> SERGIO LIMA/ARQUIVO DA EDITORA | Z50: =Tabela2[[#This Row],[ilustrador]] -> SERGIO LIMA/ARQUIVO DA EDITORA | AD50: ="Pitanguá" -> Pitanguá | AE50: ="Matemática" -> Matemática
A51: g1191_1p011m_g27_e001 | B51: EXCLUIDA | C51: GRÁFICO | D51: MIOLO | E51: 145 | F51: 1 | G51: 6 | I51: RESGATE | O51: Resgatar ilustração de um gráfico de barras sobre dia preferido na semana pelos amigos de Amanda, em g23_mdn_lt_1npm_p0145_u6, código gt2217sl_1npm_g23_mdn | P51: Excluída pela equipe. | W51: sl | X51: =IF(Tabela2[[#This Row],[sigla]]="","",VLOOKUP(Tabela2[[#This Row],[sigla]],créditos_base!B:C,2,0)) -> SERGIO LIMA/ARQUIVO DA EDITORA | Z51: =Tabela2[[#This Row],[ilustrador]] -> SERGIO LIMA/ARQUIVO DA EDITORA | AD51: ="Pitanguá" -> Pitanguá | AE51: ="Matemática" -> Matemática
A52: g1193_5p011m_g27_e001 | B52: APLICADA | C52: GRÁFICO | D52: MIOLO | E52: 154 | F52: 5 | G52: 6 | I52: AJUSTE | O52: Resgatar ilustração de gráfico de setores da página 154 do g23_mdn_lt_5npm. Código antigo gt1285_5pmm_g19_mdn AJUSTE: atualizar para padrão de contorno com fio preto no gráfico | Q52: 77 | R52: 45819 | S52: 45866 | V52: 45868 | W52: ri | X52: =IF(Tabela2[[#This Row],[sigla]]="","",VLOOKUP(Tabela2[[#This Row],[sigla]],créditos_base!B:C,2,0)) -> RONALDO LUCENA/ARQUIVO DA EDITORA | Y52: Maryane Vioto SIlva | Z52: =Tabela2[[#This Row],[ilustrador]] -> RONALDO LUCENA/ARQUIVO DA EDITORA | AA52: 14 | AB52: Resgate com ajuste | AC52: FINALIZADO | AD52: ="Pitanguá" -> Pitanguá | AE52: ="Matemática" -> Matemática
A53: g1196_5p011m_g27_e001 | B53: APLICADA | C53: GRÁFICO | D53: MIOLO | E53: 188 | F53: 5 | G53: 6 | I53: AJUSTE | O53: Resgatar ilustração do gráfico de setores da página 156 do g23_mdn_lt_5npm. Código antigo gt2233ri_5npm_g23_mdn_aj AJUSTE 1: Atualizar para padrão de contorno com fio preto no gráfico. AJUSTE 2: Atualizar o gráfico de setor com os seguintes dados: 18 a 23 anos: 36%; 24 a 34 anos: 42,9%; 35 a 44 anos: 15,6%; Acima de 45 anos: 5,5%. | Q53: 139 | R53: 45868 | S53: 45868 | V53: 45877 | W53: ri | X53: =IF(Tabela2[[#This Row],[sigla]]="","",VLOOKUP(Tabela2[[#This Row],[sigla]],créditos_base!B:C,2,0)) -> RONALDO LUCENA/ARQUIVO DA EDITORA | Y53: Gabriella Imai | Z53: =Tabela2[[#This Row],[ilustrador]] -> RONALDO LUCENA/ARQUIVO DA EDITORA | AA53: 13 | AB53: Resgate com ajuste | AC53: FINALIZADO | AD53: ="Pitanguá" -> Pitanguá | AE53: ="Matemática" -> Matemática
A54: g1205_5p011m_g27_e001 | B54: APLICADA | C54: GRÁFICO | D54: MIOLO | E54: 187 | F54: 5 | G54: 6 | I54: NOVA | O54: Ilustração de um gráfico de setores, com os seguintes dados: Sim: 15%; Não: 85% | Q54: 139 | R54: 45868 | S54: 45868 | V54: 45874 | W54: vc | X54: =IF(Tabela2[[#This Row],[sigla]]="","",VLOOKUP(Tabela2[[#This Row],[sigla]],créditos_base!B:C,2,0)) -> VINÍCIUS COSTA/ARQUIVO DA EDITORA | Z54: =Tabela2[[#This Row],[ilustrador]] -> VINÍCIUS COSTA/ARQUIVO DA EDITORA | AA54: 12 | AB54: Arte | AC54: FINALIZADO | AD54: ="Pitanguá" -> Pitanguá | AE54: ="Matemática" -> Matemática
A55: g1320_2p011m_g27_e001 | B55: APLICADA | C55: GRÁFICO | D55: MIOLO | E55: 116 | F55: 2 | G55: 7 | I55: AJUSTE | O55: Resgatar gráfico de barras sobre a Eleição para a presidência da associação do bairro, em 2022, da página 116 do g23_mdn_lt_2npm_p108a117_u5 codigo gt1009_2pmm_g19_mdn AJUSTE: compor fio contorno preto nas barras de acordo com novo padrão. | Q55: 67 | R55: 45811 | S55: 45811 | V55: 45811 | W55: sl | X55: =IF(Tabela2[[#This Row],[sigla]]="","",VLOOKUP(Tabela2[[#This Row],[sigla]],créditos_base!B:C,2,0)) -> SERGIO LIMA/ARQUIVO DA EDITORA | Y55: Rebecca Baniski | Z55: =Tabela2[[#This Row],[ilustrador]] -> SERGIO LIMA/ARQUIVO DA EDITORA | AB55: resgate com ajuste | AC55: FINALIZADO | AD55: ="Pitanguá" -> Pitanguá | AE55: ="Matemática" -> Matemática
A56: g1330_1p011m_g27_e001 | B56: APLICADA | C56: GRÁFICO | D56: MIOLO | E56: 179 | F56: 1 | G56: 7 | I56: NOVA | O56: Ilustração de um gráfico de barras horizontal no padrão da obra que represente as informações do quadro a seguir, sendo o eixo vertical o de PRODUTO e o eixo horizontal o de PREÇO (EM REAIS). Usar como base a gt3414sl_3npm_g23_mdn_aj, adaptando conforme indicado a seguir. PRODUTO PREÇO (EM REAIS) CADERNO 15 LÁPIS 2 ESTOJO 20 BORRACHA 3 | Q56: 30 | R56: 45755 | S56: 45756 | V56: 45756 | W56: km | X56: =IF(Tabela2[[#This Row],[sigla]]="","",VLOOKUP(Tabela2[[#This Row],[sigla]],créditos_base!B:C,2,0)) -> KEITHY MOSTACHI/ARQUIVO DA EDITORA | Y56: Arte | Z56: =Tabela2[[#This Row],[ilustrador]] -> KEITHY MOSTACHI/ARQUIVO DA EDITORA | AA56: 12 | AB56: padrão | AC56: FINALIZADO | AD56: ="Pitanguá" -> Pitanguá | AE56: ="Matemática" -> Matemática
A57: g1357_3p011m_g27_e001 | B57: APLICADA | C57: GRÁFICO | D57: MIOLO | E57: 180 | F57: 3 | G57: 7 | I57: NOVA | O57: Compor um pictograma que represente os dados do quadro a seguir. Classificação Quantidade de votos Ótima 40 Boa 50 Regular 80 Ruim 30 Nesse pictograma, cada figura deve valer 10 votos, conforme a ref. Compor 0 no início do pictograma. Obs: Na classificação, compor emojis que representam cada uma delas, ver ideia a seguir. | Q57: 82 | R57: 45829 | S57: 45833 | V57: 45835 | W57: rm | X57: =IF(Tabela2[[#This Row],[sigla]]="","",VLOOKUP(Tabela2[[#This Row],[sigla]],créditos_base!B:C,2,0)) -> HELOÍSA PINTARELLI/ARQUIVO DA EDITORA | Z57: =Tabela2[[#This Row],[ilustrador]] -> HELOÍSA PINTARELLI/ARQUIVO DA EDITORA | AA57: 11 | AB57: F: 27/06 | AC57: PAGO | AD57: ="Pitanguá" -> Pitanguá | AE57: ="Matemática" -> Matemática
A58: g1725_5p011m_g27_e001 | B58: APLICADA | C58: GRÁFICO | D58: MIOLO | E58: 235 | F58: 5 | G58: 9 | I58: AJUSTE | O58: Resgatar gráfico de filmes recordistas em bilheteria da página 98 do g23_mdn_lt_5npm_p096a103_u5. Código antigo gt1810ri_5npm_g23_mdn_aj AJUSTE 1: Trocar as informações do gráfico para os seguintes dados: Avatar (2009): 2,92; Vingadores Ultimato (2019): 2,8; Avatar: O Caminho da Água (2022): 2,32; Titanic (1997): 2,26; Star Wars: O Despertar da Força (2015): 2,07. Além disso, inserir os valores dos filmes em cima de suas respectivas barras. OBS: Apresentar essas informações da esquerda para a direita, em ordem decrescente. AJUSTE 2: compor fio preto em torno das barras conforme padrão | Q58: 143 | R58: 45869 | S58: 45874 | V58: 45875 | W58: ri | X58: =IF(Tabela2[[#This Row],[sigla]]="","",VLOOKUP(Tabela2[[#This Row],[sigla]],créditos_base!B:C,2,0)) -> RONALDO LUCENA/ARQUIVO DA EDITORA | Y58: Maryane Vioto Silva | Z58: =Tabela2[[#This Row],[ilustrador]] -> RONALDO LUCENA/ARQUIVO DA EDITORA | AA58: 14 | AB58: Resgate com ajuste | AC58: FINALIZADO | AD58: ="Pitanguá" -> Pitanguá | AE58: ="Matemática" -> Matemática
A59: g1926_5p011m_g27_e001 | B59: APLICADA | C59: GRÁFICO | D59: MIOLO | E59: 262 | F59: 5 | G59: 10 | I59: AJUSTE | O59: Resgatar ilustração gráfico de linhas da página 244 do g23_mdn_lt_5npm. Código antigo gt4204ri_5npm_g23_mdn_aj AJUSTE: retirar elementos em cor resposta | Q59: 144 | R59: 45873 | S59: 45880 | V59: 45882 | W59: ri | X59: =IF(Tabela2[[#This Row],[sigla]]="","",VLOOKUP(Tabela2[[#This Row],[sigla]],créditos_base!B:C,2,0)) -> RONALDO LUCENA/ARQUIVO DA EDITORA | Y59: Arte | Z59: =Tabela2[[#This Row],[ilustrador]] -> RONALDO LUCENA/ARQUIVO DA EDITORA | AA59: 13 | AB59: RESGATE OCM AJUSTE | AC59: FINALIZADO | AD59: ="Pitanguá" -> Pitanguá | AE59: ="Matemática" -> Matemática
A60: g1936_2p011m_g27_e001 | B60: APLICADA | C60: GRÁFICO | D60: MIOLO | E60: 243 | F60: 2 | G60: 10 | I60: NOVA | O60: Ilustração de um gráfico de barras verticais, com o eixo horizontal Produto e o eixo vertical Quantidade. Compor as barras, conforme a quantidade indicada a seguir. Produto Quantidade Sabonete 30 Creme dental 18 Xampu 15 Desodorante 21 Escova de dentes 12 | Q60: 56 | R60: 45805 | S60: 45805 | V60: 45806 | W60: vc | X60: =IF(Tabela2[[#This Row],[sigla]]="","",VLOOKUP(Tabela2[[#This Row],[sigla]],créditos_base!B:C,2,0)) -> VINÍCIUS COSTA/ARQUIVO DA EDITORA | Y60: Vinícius Costa | Z60: =Tabela2[[#This Row],[ilustrador]] -> VINÍCIUS COSTA/ARQUIVO DA EDITORA | AA60: 12 | AB60: Arte | AC60: FINALIZADO | AD60: ="Pitanguá" -> Pitanguá | AE60: ="Matemática" -> Matemática
A61: g1951_4p011m_g27_e001 | B61: APLICADA | C61: GRÁFICO | D61: MIOLO | E61: 256 | F61: 4 | G61: 10 | I61: AJUSTE | O61: Resgatar gráfico de barras das temperaturas de algumas capitais do g23_mdn_lt_4npm_p230 código antigo gt4632gu_4npm_g23_mdn AJUSTE: Atualizar as informações do gráfico com os seguintes dados: Aracaju, estado de Sergipe: mínima: 22; máxima: 29 Manaus, estado do Amazonas: mínima: 23; máxima: 31 Porto Alegre, estado do Rio Grande do Sul: mínima: 7; máxima: 19 Rio de Janeiro: mínima: 15; máxima: 23 São Paulo: mínima: 12; máxima: 21 | Q61: 125 | R61: 45862 | S61: 45867 | V61: 45867 | W61: gu | X61: =IF(Tabela2[[#This Row],[sigla]]="","",VLOOKUP(Tabela2[[#This Row],[sigla]],créditos_base!B:C,2,0)) -> GUSTAVO CONTI/ARQUIVO DA EDITORA | Y61: Tamires Azevedo | Z61: =Tabela2[[#This Row],[ilustrador]] -> GUSTAVO CONTI/ARQUIVO DA EDITORA | AA61: 13 | AB61: Ajuste ARTE | AC61: FINALIZADO | AD61: ="Pitanguá" -> Pitanguá | AE61: ="Matemática" -> Matemática
A62: g1961_1p011m_g27_e001 | B62: APLICADA | C62: GRÁFICO | D62: MIOLO | E62: 242 | F62: 1 | G62: 10 | I62: NOVA | O62: Ilustração de um gráfico de barras verticais para representar os dados do quadro a seguir. Usar como base a ilustração com código antigo gt1230_1pmm_g19_mdn | Q62: 37 | R62: 45775 | S62: 45776 | V62: 45777 | W62: ib | X62: =IF(Tabela2[[#This Row],[sigla]]="","",VLOOKUP(Tabela2[[#This Row],[sigla]],créditos_base!B:C,2,0)) -> INGRIDHI BORGES/ARQUIVO DA EDITORA | Y62: Arte | Z62: =Tabela2[[#This Row],[ilustrador]] -> INGRIDHI BORGES/ARQUIVO DA EDITORA | AA62: 12 | AB62: ARTE | AC62: FINALIZADO | AD62: ="Pitanguá" -> Pitanguá | AE62: ="Matemática" -> Matemática
A63: g2117_4p011m_g27_e001 | B63: EDICAO_ARTE | C63: IL TEC ARTE | D63: MIOLO | E63: 267 | F63: 4 | H63: O que você já aprendeu? | I63: AJUSTE | O63: Resgatar gráfico pesquisa sobre os animais de estimação preferidos; g23_mdn_lt_4npm_p243; código antigo gt3842_4npm_g23_mdn_re | Q63: 193 | R63: 45913 | S63: 45913 | V63: 45913 | W63: ri | X63: =IF(Tabela2[[#This Row],[sigla]]="","",VLOOKUP(Tabela2[[#This Row],[sigla]],créditos_base!B:C,2,0)) -> RONALDO LUCENA/ARQUIVO DA EDITORA | Y63: Tamires Azevedo | Z63: =Tabela2[[#This Row],[ilustrador]] -> RONALDO LUCENA/ARQUIVO DA EDITORA | AA63: 13 | AB63: arte | AC63: FINALIZADO | AD63: ="Pitanguá" -> Pitanguá | AE63: ="Matemática" -> Matemática
A64: g6102_1p011m_g27_e001 | B64: APLICADA | C64: ILUSTRAÇÃO | D64: MIOLO | E64: 253 | F64: 1 | H64: o que estudou | I64: RESGATE | O64: Resgatar gráfico da quantia em reais, poupada pelas irmãs em MARÇO/2022; g23_mdn_lt_1npm_p199; código antigo gt3043_1npm_g23_mdn | W64: ja | X64: =IF(Tabela2[[#This Row],[sigla]]="","",VLOOKUP(Tabela2[[#This Row],[sigla]],créditos_base!B:C,2,0)) -> JANAINA OLIVEIRA/ARQUIVO DA EDITORA | Z64: =Tabela2[[#This Row],[ilustrador]] -> JANAINA OLIVEIRA/ARQUIVO DA EDITORA | AD64: ="Pitanguá" -> Pitanguá | AE64: ="Matemática" -> Matemática
A65: g6106_5p011m_g27_e001 | B65: APLICADA | C65: GRÁFICO | D65: MIOLO | E65: 278 | F65: 5 | H65: O que você já aprendeu? | I65: AJUSTE | O65: Resgatar gráfico/ilustração medidas das temperaturas mínimas registradas pela prefeitura de uma cidade; g23_mdn_lt_5npm_p263; código antigo gt3826ri_5npm_g23_mdn_aj | Q65: 207 | R65: 45926 | S65: 45926 | V65: 45926 | W65: ri | X65: =IF(Tabela2[[#This Row],[sigla]]="","",VLOOKUP(Tabela2[[#This Row],[sigla]],créditos_base!B:C,2,0)) -> RONALDO LUCENA/ARQUIVO DA EDITORA | Y65: Gabriella Imai | Z65: =Tabela2[[#This Row],[ilustrador]] -> RONALDO LUCENA/ARQUIVO DA EDITORA | AA65: 13 | AB65: resgate com ajuste | AD65: ="Pitanguá" -> Pitanguá | AE65: ="Matemática" -> Matemática
A66: g6107_5p011m_g27_e001 | B66: APLICADA | C66: GRÁFICO | D66: MIOLO | E66: 278 | F66: 5 | H66: O que você já aprendeu? | I66: AJUSTE | O66: Resgatar gráfico/ilustração medidas das temperaturas máximas registradas pela prefeitura de uma cidade; g23_mdn_lt_5npm_p263; código antigo gt3825ri_5npm_g23_mdn_aj | Q66: 207 | R66: 45926 | S66: 45926 | V66: 45926 | W66: ri | X66: =IF(Tabela2[[#This Row],[sigla]]="","",VLOOKUP(Tabela2[[#This Row],[sigla]],créditos_base!B:C,2,0)) -> RONALDO LUCENA/ARQUIVO DA EDITORA | Y66: Gabriella Imai | Z66: =Tabela2[[#This Row],[ilustrador]] -> RONALDO LUCENA/ARQUIVO DA EDITORA | AA66: 13 | AB66: resgate com ajuste | AD66: ="Pitanguá" -> Pitanguá | AE66: ="Matemática" -> Matemática
A67: g6114_3p011m_g27_e001 | B67: APLICADA | C67: GRÁFICO | D67: MIOLO | E67: 17 | F67: 3 | G67: OVJS | I67: AJUSTE | O67: Resgatar ilustração do gráfico de barras com uma barra verde e as outras para o estudante pintar da página 9 do g23_mdn_lt_3npm. Código antigo gt0248pn_3npm_g23_mdn AJUSTE: tirar a cor resposta da imagem. | Q67: 47 | R67: 45797 | S67: 45797 | V67: 45797 | W67: pn | X67: =IF(Tabela2[[#This Row],[sigla]]="","",VLOOKUP(Tabela2[[#This Row],[sigla]],créditos_base!B:C,2,0)) -> RAFAELA PANISSA/ARQUIVO DA EDITORA | Y67: Vinícius Costa | Z67: =Tabela2[[#This Row],[ilustrador]] -> RAFAELA PANISSA/ARQUIVO DA EDITORA | AA67: 14 | AB67: Resgate com ajuste | AC67: FINALIZADO | AD67: ="Pitanguá" -> Pitanguá | AE67: ="Matemática" -> Matemática
A68: g6203_5p011m_g27_e001 | B68: APLICADA | C68: GRÁFICO | D68: MP-E | F68: 5 | H68: O que você já sabe? | I68: NOVA | O68: Gráfico de colunas duplas do padrão (com fio preto em torno das barras). Eixo vertical: “Quantidade de votos”; eixo horizontal: “Gênero”, com os nomes e valores: animação (4; 5), aventura (2; 4), comédia (3; 3), ação (1; 6), outros (3; 1). Compor legenda com as respectivas cores das colunas de acordo com a referência. Atenção com o tamanho do gráfico pois vai entrar no rodapé do MPU e não deve ultrapassar 5 cm de altura | Q68: 177 | R68: 45903 | S68: 45903 | V68: 45904 | W68: gx | X68: =IF(Tabela2[[#This Row],[sigla]]="","",VLOOKUP(Tabela2[[#This Row],[sigla]],créditos_base!B:C,2,0)) -> GABRIELLA IMAI/ARQUIVO DA EDITORA | Z68: =Tabela2[[#This Row],[ilustrador]] -> GABRIELLA IMAI/ARQUIVO DA EDITORA | AA68: 12 | AB68: padrão | AC68: FINALIZADO | AD68: ="Pitanguá" -> Pitanguá | AE68: ="Matemática" -> Matemática
A69: g6208_5p011m_g27_e001 | B69: APLICADA | C69: GRÁFICO | D69: MP-E | F69: 5 | G69: 1 | I69: NOVA | O69: Il. de um gráfico de colunas do padrão, com fio contorno preto nas barras. A imagem não pode ter mais do que 5 cm de altura, pois vai entrar no rodapé do MPU. No eixo horizontal indicar Alimento; no eixo vertical indicar Quantidade (em kg). O eixo vertical deve ir de 0 a 160, de 20 em 20. Os valores são: Arroz: 123; Feijão: 89; Macarrão: 145 | Q69: 177 | R69: 45903 | S69: 45903 | V69: 45904 | W69: gx | X69: =IF(Tabela2[[#This Row],[sigla]]="","",VLOOKUP(Tabela2[[#This Row],[sigla]],créditos_base!B:C,2,0)) -> GABRIELLA IMAI/ARQUIVO DA EDITORA | Z69: =Tabela2[[#This Row],[ilustrador]] -> GABRIELLA IMAI/ARQUIVO DA EDITORA | AA69: 12 | AB69: padrão | AC69: FINALIZADO | AD69: ="Pitanguá" -> Pitanguá | AE69: ="Matemática" -> Matemática
A70: g6213_5p011m_g27_e001 | B70: AVALIANDO | C70: GRÁFICO | D70: MP-E | E70: 90 | F70: 5 | G70: 4 | I70: NOVA | O70: Ilustração de um gráfico de colunas verticais com os dados do quadro a seguir. Eixo horizontal: “Brincadeira” e vertical “Quantidade de votos”. Eixo vertical de 5 em 5, de 0 a 40. Brincadeira Quantidade de votos Pular corda 10; Dança das cadeiras 30; Estoura-bexiga 21; Torta na cara 39 | Q70: 197 | R70: 45922 | S70: 45922 | V70: 45922 | W70: pn | X70: =IF(Tabela2[[#This Row],[sigla]]="","",VLOOKUP(Tabela2[[#This Row],[sigla]],créditos_base!B:C,2,0)) -> RAFAELA PANISSA/ARQUIVO DA EDITORA | Z70: =Tabela2[[#This Row],[ilustrador]] -> RAFAELA PANISSA/ARQUIVO DA EDITORA | AA70: 12 | AB70: Arte | AC70: FINALIZADO | AD70: ="Pitanguá" -> Pitanguá | AE70: ="Matemática" -> Matemática
A71: g6215_2p011m_g27_e001 | B71: APLICADA | C71: GRÁFICO | D71: MP-E | E71: 141 | F71: 2 | G71: 5 | I71: AJUSTE | O71: Resgatar gráfico de barras, na página 75 do g23_mdn_lt_2npm_p070a078_u3; código antigo gt1005sl_2npm_g23_mdn_aj AJUSTE1: colorir as barras de outra cor, que não seja magenta. AJUSTE 2: O gráfico vai entrar no MPU, não deve passar de 5 cm de altura. AJUSTE3: inserir as figuras geométricas abaixo de cada coluna do gráfico, como mostra o print. Utilizar i0925_2p011m_g27_e001 (cubo);i0926_2p011m_g27_e001 (paralelepípedo); i0927_2p011m_g27_e001 (cilindro); i0928_2p011m_g27_e001 (esfera); i0929_2p011m_g27_e001 (cone); i0925_2p011m_g27_e001 (pirâmide). | Q71: 120 | R71: 45860 | S71: 45861 | V71: 45861 | W71: sl | X71: =IF(Tabela2[[#This Row],[sigla]]="","",VLOOKUP(Tabela2[[#This Row],[sigla]],créditos_base!B:C,2,0)) -> SERGIO LIMA/ARQUIVO DA EDITORA | Y71: Nicolas Furtado | Z71: =Tabela2[[#This Row],[ilustrador]] -> SERGIO LIMA/ARQUIVO DA EDITORA | AA71: 14 | AB71: resgate ajuste | AC71: FINALIZADO | AD71: ="Pitanguá" -> Pitanguá | AE71: ="Matemática" -> Matemática
A72: g6237_3p011m_g27_e001 | B72: APLICADA | C72: GRÁFICO | D72: MP-E | E72: 267 | F72: 3 | H72: O que você já aprendeu? | I72: NOVA | O72: Il gráfico de colunas no padrão da obra com as indicações a seguir. O eixo horizontal deve ser Atividade e o eixo vertical Quantidade de estudantes. Compor as colunas de acordo com os dados. Praticar uma arte marcial - 12; Tocar um instrumento musical- 15; Dançar – 7; Outros – 8. Observação: O gráfico não deve ter mais do que 5 cm de altura, pois vai entrar no MPU. Ver referência. | Q72: 178 | R72: 45904 | S72: 45905 | V72: 45905 | W72: vc | X72: =IF(Tabela2[[#This Row],[sigla]]="","",VLOOKUP(Tabela2[[#This Row],[sigla]],créditos_base!B:C,2,0)) -> VINÍCIUS COSTA/ARQUIVO DA EDITORA | Z72: =Tabela2[[#This Row],[ilustrador]] -> VINÍCIUS COSTA/ARQUIVO DA EDITORA | AA72: 12 | AB72: arte | AC72: FINALIZADO | AD72: ="Pitanguá" -> Pitanguá | AE72: ="Matemática" -> Matemática
A73: i0101_4p011m_g27_e001 | B73: APLICADA | C73: IL TEC ARTE | D73: MIOLO | E73: 12 | F73: 4 | H73: o que ja sabe | I73: AJUSTE | O73: Resgatar ilustração da reta numérica do g23_mdn_lt_4npm_p006 código antigo it0310_3npm_m20_mdn AJUSTE: Retirar as respostas | Q73: 9 | R73: 45733 | S73: 45736 | V73: 45736 | W73: sl | X73: =IF(Tabela2[[#This Row],[sigla]]="","",VLOOKUP(Tabela2[[#This Row],[sigla]],créditos_base!B:C,2,0)) -> SERGIO LIMA/ARQUIVO DA EDITORA | Y73: Keithy Mostachi | Z73: =Tabela2[[#This Row],[ilustrador]] -> SERGIO LIMA/ARQUIVO DA EDITORA | AA73: 13 | AD73: ="Pitanguá" -> Pitanguá | AE73: ="Matemática" -> Matemática
A74: i0102_1p011m_g27_e001 | B74: APLICADA | C74: ILUSTRAÇÃO | D74: MIOLO | E74: 20 | F74: 1 | G74: 1 | I74: AJUSTE | O74: Resgatar e ajustar ilustração de crianças brincando em um pátio, em g23_mdn_lt_1npm_p010a020_u1, página 12. Código antigo: i0324za_1pmm_g19_mdn AJUSTE 1: Ajustar a sangra fechando o grid da página feita como feito na leitura prévia da Arte. (Ver referência). AJUSTE 2: Trocar o tom da cor da pele da menina que está embaixo da mesa. Ela deve ser negra. AJUSTE 3: Inserir um adulto na cena. | Q74: 25 | R74: 45751 | S74: 45751 | V74: 45754 | W74: za | X74: =IF(Tabela2[[#This Row],[sigla]]="","",VLOOKUP(Tabela2[[#This Row],[sigla]],créditos_base!B:C,2,0)) -> JORGE ZAIBA/ARQUIVO DA EDITORA | Y74: Bruna Campos | Z74: =Tabela2[[#This Row],[ilustrador]] -> JORGE ZAIBA/ARQUIVO DA EDITORA | AA74: 13 | AB74: resgate com ajuste | AC74: FINALIZADO | AD74: ="Pitanguá" -> Pitanguá | AE74: ="Matemática" -> Matemática
A75: i0102_3p011m_g27_e001 | B75: APLICADA | C75: ILUSTRAÇÃO | D75: MIOLO | E75: 12 | F75: 3 | G75: 1 | I75: AJUSTE | O75: resgatar ilustração de pessoas numa praia em espelho veio do g23_mdn_lt_3npm_p012 codigo antigo i0236ci_3pmm_g19_mdn_ef_ly AJUSTE: Na ilustração, cropar conforme o print a seguir. Além disso, trocar carrinho de sorvete por carrinho do milho. | Q75: 78 | R75: 45820 | V75: 45750 | W75: ci | X75: =IF(Tabela2[[#This Row],[sigla]]="","",VLOOKUP(Tabela2[[#This Row],[sigla]],créditos_base!B:C,2,0)) -> CAUÊ ZUNCHINI/ARQUIVO DA EDITORA | Y75: Keithy Mostachi | Z75: =Tabela2[[#This Row],[ilustrador]] -> CAUÊ ZUNCHINI/ARQUIVO DA EDITORA | AA75: 13 | AB75: resgate com ajuste | AC75: FINALIZADO | AD75: ="Pitanguá" -> Pitanguá | AE75: ="Matemática" -> Matemática
A76: i0102_4p011m_g27_e001 | B76: APLICADA | C76: IL TEC ARTE | D76: MIOLO | E76: 12 | F76: 4 | H76: o que ja sabe | I76: RESGATE | O76: Resgatar ilustração da planificação do g23_mdn_lt_4npm_p006 código antigo it0221sl_4npm_g23_mdn | W76: sl | X76: =IF(Tabela2[[#This Row],[sigla]]="","",VLOOKUP(Tabela2[[#This Row],[sigla]],créditos_base!B:C,2,0)) -> SERGIO LIMA/ARQUIVO DA EDITORA | Z76: =Tabela2[[#This Row],[ilustrador]] -> SERGIO LIMA/ARQUIVO DA EDITORA | AD76: ="Pitanguá" -> Pitanguá | AE76: ="Matemática" -> Matemática
A77: i0103_1p011m_g27_e001 | B77: EXCLUIDA | C77: ILUSTRAÇÃO | D77: MIOLO | E77: 13 | F77: 1 | G77: 1 | I77: RESGATE | O77: Resgatar ilustração da bela adormecida junto com o principe em um quarto e uma bruxa na janela, em g23_mdn_lt_1npm_p010a020_u1, página 13, conforme referência. Código antigo: i0221za_1pmm_g19_mdn | P77: Excluída pela equipe. | S77: 45722 | W77: za | X77: =IF(Tabela2[[#This Row],[sigla]]="","",VLOOKUP(Tabela2[[#This Row],[sigla]],créditos_base!B:C,2,0)) -> JORGE ZAIBA/ARQUIVO DA EDITORA | Y77: Bruna Campos | Z77: =Tabela2[[#This Row],[ilustrador]] -> JORGE ZAIBA/ARQUIVO DA EDITORA | AA77: 14 | AC77: PREVISAO | AD77: ="Pitanguá" -> Pitanguá | AE77: ="Matemática" -> Matemática
A78: i0103_2p011m_g27_e001 | B78: APLICADA | C78: ILUSTRAÇÃO | D78: MIOLO | F78: 2 | G78: 1 | I78: RESGATE | O78: Resgatar ilustração de cenário do fundo do mar, na página 12 do g23_mdn_lt_2npm_p010a017_u1 i0278gn_2pmm_g19_mdn | W78: gn | X78: =IF(Tabela2[[#This Row],[sigla]]="","",VLOOKUP(Tabela2[[#This Row],[sigla]],créditos_base!B:C,2,0)) -> GUILHERME ARANEGA/ARQUIVO DA EDITORA | Z78: =Tabela2[[#This Row],[ilustrador]] -> GUILHERME ARANEGA/ARQUIVO DA EDITORA | AD78: ="Pitanguá" -> Pitanguá | AE78: ="Matemática" -> Matemática
A79: i0104_1p011m_g27_e001 | B79: APLICADA | C79: ILUSTRAÇÃO | D79: MIOLO | E79: 13 | F79: 1 | G79: 1 | I79: RESGATE | O79: Resgatar ilustração de um quarto cheio de brinquedos espalhados, em g23_mdn_lt_1npm_p010a020_u1, página 13, conforme referência. Código antigo: i0323za_1pmm_g19_mdn | W79: za | X79: =IF(Tabela2[[#This Row],[sigla]]="","",VLOOKUP(Tabela2[[#This Row],[sigla]],créditos_base!B:C,2,0)) -> JORGE ZAIBA/ARQUIVO DA EDITORA | Z79: =Tabela2[[#This Row],[ilustrador]] -> JORGE ZAIBA/ARQUIVO DA EDITORA | AD79: ="Pitanguá" -> Pitanguá | AE79: ="Matemática" -> Matemática
A80: i0104_4p011m_g27_e001 | B80: APLICADA | C80: IL TEC ARTE | D80: MIOLO | E80: 13 | F80: 4 | H80: o que ja sabe | I80: AJUSTE | O80: Resgatar ilustração da malha quadriculada do g23_mdn_lt_4npm_p007 código antigo i0955zz_3npm_m20_mdn | Q80: 215 | R80: 45932 | S80: 45932 | V80: 45932 | W80: sl | X80: =IF(Tabela2[[#This Row],[sigla]]="","",VLOOKUP(Tabela2[[#This Row],[sigla]],créditos_base!B:C,2,0)) -> SERGIO LIMA/ARQUIVO DA EDITORA | Y80: Gabriella Imai | Z80: =Tabela2[[#This Row],[ilustrador]] -> SERGIO LIMA/ARQUIVO DA EDITORA | AA80: 13 | AB80: resgate c ajuste | AD80: ="Pitanguá" -> Pitanguá | AE80: ="Matemática" -> Matemática
A81: i0104_5p011m_g27_e001 | B81: APLICADA | C81: ILUSTRAÇÃO | D81: MIOLO | E81: 20 | F81: 5 | G81: 1 | I81: AJUSTE | O81: Resgatar ilustração de papiro exibindo as representações numéricas desde o século 12 até a atualidade. Veio de: g23_mdn_lt_5npm_p010. Código antigo: i0203aa_5pmm_g19_mdn_ef AJUSTE: Inserir título no quadro “Transformação da escrita dos algarismos” e excluir as mãos laterais que estão segurando o papiro. | Q81: 126 | R81: 45863 | S81: 45867 | V81: 45869 | W81: aa | X81: =IF(Tabela2[[#This Row],[sigla]]="","",VLOOKUP(Tabela2[[#This Row],[sigla]],créditos_base!B:C,2,0)) -> ANDRÉ AGUIAR/ARQUIVO DA EDITORA | Y81: Arte | Z81: =Tabela2[[#This Row],[ilustrador]] -> ANDRÉ AGUIAR/ARQUIVO DA EDITORA | AA81: 13 | AB81: RESGATE COM AJUSTAE | AC81: FINALIZADO | AD81: ="Pitanguá" -> Pitanguá | AE81: ="Matemática" -> Matemática
A82: i0105_2p011m_g27_e001 | B82: APLICADA | C82: ILUSTRAÇÃO | D82: MIOLO | E82: 13 | F82: 2 | G82: 1 | I82: RESGATE | O82: Resgatar ilustração de caixa vazia, na página 13 do g23_mdn_lt_2npm_p010a017_u1 i0205mk_2pmm_g19_mdn | W82: mk | X82: =IF(Tabela2[[#This Row],[sigla]]="","",VLOOKUP(Tabela2[[#This Row],[sigla]],créditos_base!B:C,2,0)) -> NATANAELE BILMAIA/ARQUIVO DA EDITORA | Z82: =Tabela2[[#This Row],[ilustrador]] -> NATANAELE BILMAIA/ARQUIVO DA EDITORA | AD82: ="Pitanguá" -> Pitanguá | AE82: ="Matemática" -> Matemática
A83: i0105_4p011m_g27_e001 | B83: EXCLUIDA | C83: IL TEC ARTE | D83: MIOLO | E83: 13 | F83: 4 | H83: o que ja sabe | I83: RESGATE | O83: Resgatar ilustração do esquema do g23_mdn_lt_4npm_p007 código antigo i0224_4npm_g23_mdn_re | P83: Excluída pela equipe. | W83: sl | X83: =IF(Tabela2[[#This Row],[sigla]]="","",VLOOKUP(Tabela2[[#This Row],[sigla]],créditos_base!B:C,2,0)) -> SERGIO LIMA/ARQUIVO DA EDITORA | Z83: =Tabela2[[#This Row],[ilustrador]] -> SERGIO LIMA/ARQUIVO DA EDITORA | AD83: ="Pitanguá" -> Pitanguá | AE83: ="Matemática" -> Matemática
A84: i0105_5p011m_g27_e001 | B84: APLICADA | C84: IL TEC ARTE | D84: MIOLO | E84: 21 | F84: 5 | G84: 1 | I84: RESGATE | O84: Resgatar ilustração de um cubinho do material dourado. Veio de: g23_mdn_lt_5npm_p013. Código antigo:i0204rn_5pmm_g19_mdn | W84: zz | X84: =IF(Tabela2[[#This Row],[sigla]]="","",VLOOKUP(Tabela2[[#This Row],[sigla]],créditos_base!B:C,2,0)) -> VER DOCUMENTO DE ILS. TÉCNICAS | Z84: TAMIRES AZEVEDO/ARQUIVO DA EDITORA | AD84: ="Pitanguá" -> Pitanguá | AE84: ="Matemática" -> Matemática
A85: i0106_2p011m_g27_e001 | B85: APLICADA | C85: ILUSTRAÇÃO | D85: MIOLO | E85: 13 | F85: 2 | G85: 1 | I85: RESGATE | O85: Resgatar ilustração de caixa com uma bolinha, na página 13 do g23_mdn_lt_2npm_p010a017_u1 i0206mk_2pmm_g19_mdn | W85: mk | X85: =IF(Tabela2[[#This Row],[sigla]]="","",VLOOKUP(Tabela2[[#This Row],[sigla]],créditos_base!B:C,2,0)) -> NATANAELE BILMAIA/ARQUIVO DA EDITORA | Z85: =Tabela2[[#This Row],[ilustrador]] -> NATANAELE BILMAIA/ARQUIVO DA EDITORA | AD85: ="Pitanguá" -> Pitanguá | AE85: ="Matemática" -> Matemática
A86: i0106_3p011m_g27_e001 | B86: APLICADA | C86: ILUSTRAÇÃO | D86: MIOLO | E86: 15 | F86: 3 | G86: 1 | I86: RESGATE | O86: resgatar il de menino medindo sua mao veio do g23_mdn_lt_3npm_p015 código antigo i0211cz_3pmm_g19_mdn | W86: cz | X86: =IF(Tabela2[[#This Row],[sigla]]="","",VLOOKUP(Tabela2[[#This Row],[sigla]],créditos_base!B:C,2,0)) -> CLAUDIA SOUZA/ARQUIVO DA EDITORA | Z86: =Tabela2[[#This Row],[ilustrador]] -> CLAUDIA SOUZA/ARQUIVO DA EDITORA | AD86: ="Pitanguá" -> Pitanguá | AE86: ="Matemática" -> Matemática
A87: i0106_4p011m_g27_e001 | B87: APLICADA | C87: IL TEC ARTE | D87: MIOLO | E87: 15 | F87: 4 | H87: o que ja sabe | I87: RESGATE | O87: Resgatar ilustração do relógio do g23_mdn_lt_4npm_p009 código antigo i0225zz_4npm_g23_mdn_aj | W87: rr | X87: =IF(Tabela2[[#This Row],[sigla]]="","",VLOOKUP(Tabela2[[#This Row],[sigla]],créditos_base!B:C,2,0)) -> ROGÉRIO CASAGRANDE/ARQUIVO DA EDITORA | Z87: =Tabela2[[#This Row],[ilustrador]] -> ROGÉRIO CASAGRANDE/ARQUIVO DA EDITORA | AD87: ="Pitanguá" -> Pitanguá | AE87: ="Matemática" -> Matemática
A88: i0106_5p011m_g27_e001 | B88: APLICADA | C88: IL TEC ARTE | D88: MIOLO | E88: 21 | F88: 5 | G88: 1 | I88: RESGATE | O88: Resgatar ilustração de uma barra do material dourado. Veio de: g23_mdn_lt_5npm_p013. Código antigo:i0205rn_5pmm_g19_mdn | W88: zz | X88: =IF(Tabela2[[#This Row],[sigla]]="","",VLOOKUP(Tabela2[[#This Row],[sigla]],créditos_base!B:C,2,0)) -> VER DOCUMENTO DE ILS. TÉCNICAS | Z88: TAMIRES AZEVEDO/ARQUIVO DA EDITORA | AD88: ="Pitanguá" -> Pitanguá | AE88: ="Matemática" -> Matemática
A89: i0107_1p011m_g27_e001 | B89: APLICADA | C89: ILUSTRAÇÃO | D89: MIOLO | E89: 15 | F89: 1 | G89: 1 | I89: RESGATE | O89: Resgatar ilustração de 5 crianças em fila e uma professora na frente da filha, em g23_mdn_lt_1npm_p010a020_u1, página 15, conforme referência. Código antigo: i0226sh_1pmm_g19_mdn | W89: sh | X89: =IF(Tabela2[[#This Row],[sigla]]="","",VLOOKUP(Tabela2[[#This Row],[sigla]],créditos_base!B:C,2,0)) -> SONIA HORN/ARQUIVO DA EDITORA | Z89: =Tabela2[[#This Row],[ilustrador]] -> SONIA HORN/ARQUIVO DA EDITORA | AD89: ="Pitanguá" -> Pitanguá | AE89: ="Matemática" -> Matemática
A90: i0107_2p011m_g27_e001 | B90: APLICADA | C90: ILUSTRAÇÃO | D90: MIOLO | E90: 13 | F90: 2 | G90: 1 | I90: RESGATE | O90: Resgatar ilustração de caixa com duas bolinhas, na página 13 do g23_mdn_lt_2npm_p010a017_u1 i0207mk_2pmm_g19_mdn | W90: mk | X90: =IF(Tabela2[[#This Row],[sigla]]="","",VLOOKUP(Tabela2[[#This Row],[sigla]],créditos_base!B:C,2,0)) -> NATANAELE BILMAIA/ARQUIVO DA EDITORA | Z90: =Tabela2[[#This Row],[ilustrador]] -> NATANAELE BILMAIA/ARQUIVO DA EDITORA | AD90: ="Pitanguá" -> Pitanguá | AE90: ="Matemática" -> Matemática
A91: i0107_3p011m_g27_e001 | B91: APLICADA | C91: ILUSTRAÇÃO | D91: MIOLO | E91: 15 | F91: 3 | G91: 1 | I91: RESGATE | O91: resgatar il de menino vendo calendário veio do g23_mdn_lt_3npm_p015 código antigo i0212cz_3pmm_g19_mdn | W91: cz | X91: =IF(Tabela2[[#This Row],[sigla]]="","",VLOOKUP(Tabela2[[#This Row],[sigla]],créditos_base!B:C,2,0)) -> CLAUDIA SOUZA/ARQUIVO DA EDITORA | Z91: =Tabela2[[#This Row],[ilustrador]] -> CLAUDIA SOUZA/ARQUIVO DA EDITORA | AD91: ="Pitanguá" -> Pitanguá | AE91: ="Matemática" -> Matemática
A92: i0107_4p011m_g27_e001 | B92: APLICADA | C92: IL TEC ARTE | D92: MIOLO | E92: 15 | F92: 4 | H92: o que ja sabe | I92: RESGATE | O92: Resgatar ilustração do relógio do g23_mdn_lt_4npm_p009 código antigo i0226zz_4npm_g23_mdn_aj | W92: rr | X92: =IF(Tabela2[[#This Row],[sigla]]="","",VLOOKUP(Tabela2[[#This Row],[sigla]],créditos_base!B:C,2,0)) -> ROGÉRIO CASAGRANDE/ARQUIVO DA EDITORA | Z92: =Tabela2[[#This Row],[ilustrador]] -> ROGÉRIO CASAGRANDE/ARQUIVO DA EDITORA | AD92: ="Pitanguá" -> Pitanguá | AE92: ="Matemática" -> Matemática
A93: i0107_5p011m_g27_e001 | B93: APLICADA | C93: IL TEC ARTE | D93: MIOLO | E93: 21 | F93: 5 | G93: 1 | I93: RESGATE | O93: Resgatar ilustração de uma placa do material dourado. Veio de: g23_mdn_lt_5npm_p013. Código antigo:i0206rn_5pmm_g19_mdn | W93: zz | X93: =IF(Tabela2[[#This Row],[sigla]]="","",VLOOKUP(Tabela2[[#This Row],[sigla]],créditos_base!B:C,2,0)) -> VER DOCUMENTO DE ILS. TÉCNICAS | Z93: TAMIRES AZEVEDO/ARQUIVO DA EDITORA | AD93: ="Pitanguá" -> Pitanguá | AE93: ="Matemática" -> Matemática
A94: i0108_1p011m_g27_e001 | B94: APLICADA | C94: ILUSTRAÇÃO | D94: MIOLO | E94: 15 | F94: 1 | G94: 1 | I94: RESGATE | O94: Resgatar ilustração uma menina regando flores e outra dentro de uma casa, na janela, em g23_mdn_lt_1npm_p010a020_u1, página 15, conforme referência. Código antigo: i0227sh_1pmm_g19_mdn | W94: sh | X94: =IF(Tabela2[[#This Row],[sigla]]="","",VLOOKUP(Tabela2[[#This Row],[sigla]],créditos_base!B:C,2,0)) -> SONIA HORN/ARQUIVO DA EDITORA | Z94: =Tabela2[[#This Row],[ilustrador]] -> SONIA HORN/ARQUIVO DA EDITORA | AD94: ="Pitanguá" -> Pitanguá | AE94: ="Matemática" -> Matemática
A95: i0108_2p011m_g27_e001 | B95: APLICADA | C95: ILUSTRAÇÃO | D95: MIOLO | E95: 13 | F95: 2 | G95: 1 | I95: RESGATE | O95: Resgatar ilustração de caixa com três bolinhas, na página 13 do g23_mdn_lt_2npm_p010a017_u1 i0208mk_2pmm_g19_mdn | W95: mk | X95: =IF(Tabela2[[#This Row],[sigla]]="","",VLOOKUP(Tabela2[[#This Row],[sigla]],créditos_base!B:C,2,0)) -> NATANAELE BILMAIA/ARQUIVO DA EDITORA | Z95: =Tabela2[[#This Row],[ilustrador]] -> NATANAELE BILMAIA/ARQUIVO DA EDITORA | AD95: ="Pitanguá" -> Pitanguá | AE95: ="Matemática" -> Matemática
A96: i0108_3p011m_g27_e001 | B96: APLICADA | C96: ILUSTRAÇÃO | D96: MIOLO | E96: 15 | F96: 3 | G96: 1 | I96: RESGATE | O96: resgatar il de mulher falando com o balconista veio do g23_mdn_lt_3npm_p015 código antigo i0213cz_3pmm_g19_mdn | W96: cz | X96: =IF(Tabela2[[#This Row],[sigla]]="","",VLOOKUP(Tabela2[[#This Row],[sigla]],créditos_base!B:C,2,0)) -> CLAUDIA SOUZA/ARQUIVO DA EDITORA | Z96: =Tabela2[[#This Row],[ilustrador]] -> CLAUDIA SOUZA/ARQUIVO DA EDITORA | AD96: ="Pitanguá" -> Pitanguá | AE96: ="Matemática" -> Matemática
A97: i0108_4p011m_g27_e001 | B97: APLICADA | C97: IL TEC ARTE | D97: MIOLO | E97: 15 | F97: 4 | H97: o que ja sabe | I97: RESGATE | O97: Resgatar ilustração do relógio do g23_mdn_lt_4npm_p009 código antigo i0227zz_4npm_g23_mdn_aj | W97: rr | X97: =IF(Tabela2[[#This Row],[sigla]]="","",VLOOKUP(Tabela2[[#This Row],[sigla]],créditos_base!B:C,2,0)) -> ROGÉRIO CASAGRANDE/ARQUIVO DA EDITORA | Z97: =Tabela2[[#This Row],[ilustrador]] -> ROGÉRIO CASAGRANDE/ARQUIVO DA EDITORA | AD97: ="Pitanguá" -> Pitanguá | AE97: ="Matemática" -> Matemática
A98: i0108_5p011m_g27_e001 | B98: APLICADA | C98: IL TEC ARTE | D98: MIOLO | E98: 21 | F98: 5 | G98: 1 | I98: RESGATE | O98: Resgatar ilustração de um cubo do material dourado. Veio de: g23_mdn_lt_5npm_p013. Código antigo:i0207rn_5pmm_g19_mdn | W98: zz | X98: =IF(Tabela2[[#This Row],[sigla]]="","",VLOOKUP(Tabela2[[#This Row],[sigla]],créditos_base!B:C,2,0)) -> VER DOCUMENTO DE ILS. TÉCNICAS | Z98: TAMIRES AZEVEDO/ARQUIVO DA EDITORA | AD98: ="Pitanguá" -> Pitanguá | AE98: ="Matemática" -> Matemática
A99: i0109_1p011m_g27_e001 | B99: APLICADA | C99: ILUSTRAÇÃO | D99: MIOLO | E99: 16 | F99: 1 | G99: 1 | I99: RESGATE | O99: Resgatar ilustração de um adulto tirando foto de 4 crianças, na janela, em g23_mdn_lt_1npm_p010a020_u1, página 16, conforme referência. Código antigo: i0219za_1npm_g23_mdn_aj | W99: za | X99: =IF(Tabela2[[#This Row],[sigla]]="","",VLOOKUP(Tabela2[[#This Row],[sigla]],créditos_base!B:C,2,0)) -> JORGE ZAIBA/ARQUIVO DA EDITORA | Z99: =Tabela2[[#This Row],[ilustrador]] -> JORGE ZAIBA/ARQUIVO DA EDITORA | AD99: ="Pitanguá" -> Pitanguá | AE99: ="Matemática" -> Matemática
A100: i0109_2p011m_g27_e001 | B100: APLICADA | C100: ILUSTRAÇÃO | D100: MIOLO | E100: 13 | F100: 2 | G100: 1 | I100: RESGATE | O100: Resgatar ilustração de caixa com cinco bolinhas, na página 13 do g23_mdn_lt_2npm_p010a017_u1 i0210mk_2pmm_g19_mdn | W100: mk | X100: =IF(Tabela2[[#This Row],[sigla]]="","",VLOOKUP(Tabela2[[#This Row],[sigla]],créditos_base!B:C,2,0)) -> NATANAELE BILMAIA/ARQUIVO DA EDITORA | Z100: =Tabela2[[#This Row],[ilustrador]] -> NATANAELE BILMAIA/ARQUIVO DA EDITORA | AD100: ="Pitanguá" -> Pitanguá | AE100: ="Matemática" -> Matemática
...

Sheet créditos_base
A1: CRÉDITOS GERAIS DA MODERNA PARA REFERÊNCIA - EF1
A2: Nome do ilustrador | B2: Sigla Arte | C2: Crédito
A3: Nome do ilustrador | B3: Sigla Arte | C3: Crédito
A4: Acervo da editora | B4: xx | C4: ARQUIVO DA EDITORA
A5: Sigla ZZ (ver documento de ils. técnicas) | B5: zz | C5: VER DOCUMENTO DE ILS. TÉCNICAS
A6: ILUSTRAÇOES DE PROVAS OFICIAIS (somente se não houver crédito) | B6: yv | C6: NOME DA UNIVERSIDADE/ANO - UNICAMP 2024 NOME DO ILUSTRADOR (AJUSTE)/ARQUIVO DA EDITORA/UNIVERSIDADE ANO
A7: ILUSTRAÇÕES DE PLACAS DE TRÂNSITO | B7: yy | C7: NOME DO ILUSTRADOR/ARQUIVO DA EDITORA
A8: ILUSTRAÇÕES DE BANDEIRAS DE PAÍS | B8: yp | C8: NOME DO ILUSTRADOR/ARQUIVO DA EDITORA
A9: ILUSTRAÇÕES DE BANDEIRAS DE ESTADO | B9: ye | C9: NOME DO ILUSTRADOR/ARQUIVO DA EDITORA
A10: ILUSTRAÇÕES GERADAS POR PROGRAMAS C/ IA | B10: ia | C10: ARQUIVO DA EDITORA
A11: Arte | B11: a | C11: ARTE
A12: 3 Pixel Studio | B12: px | C12: ROBSON OLIVIERIA/ARQUIVO DA EDITORA
A13: A7 Estudio | B13: ao | C13: JORGE RIBEIRO/ARQUIVO DA EDITORA
... A41: Beatriz Mayumi | B41: bm | C41: BEATRIZ MAYUMI/ARQUIVO DA EDITORA
A42: Belli Studio Design | B42: bl
A43: Bernardo França | B43: be | C43: BERNARDO FRANÇA/ARQUIVO DA EDITORA
A44: Bianca Nazari | B44: bi | C44: BIANCA NAZARI/ARQUIVO DA EDITORA
A45: Brenda Bossato | B45: bd | C45: BRENDA BOSSATO/ARQUIVO DA EDITORA
A46: Brenda Goes | B46: bg | C46: BRENDA GOES/ARQUIVO DA EDITORA
A47: Bruna Campos | B47: bp | C47: BRUNA CAMPOS/ARQUIVO DA EDITORA
A48: Brunna Mancuso | B48: bs | C48: BRUNNA MANCUSO/ARQUIVO DA EDITORA
A49: Bruna Menezes | B49: bz | C49: BRUNA MENEZES/ARQUIVO DA EDITORA
A50: Bruno Badain | B50: bb | C50: BRUNO BADAIN/ARQUIVO DA EDITORA
A51: Bruno H. S. Cerkuenik | B51: bc | C51: BRUNO CERKUENIK/ARQUIVO DA EDITORA
A52: Bruno Nunes Coelho | B52: bn | C52: BRUNO NUNES/ARQUIVO DA EDITORA
A53: Bruno Oliveira Sampaio | B53: br | C53: BRUNO SAMPAIO/ARQUIVO DA EDITORA
A54: Bruno Rosal de Vasconcelos | B54: bu
A55: Caio Hideki Takaso Tanaka | B55: ct | C55: CAIO TANAKA/ARQUIVO DA EDITORA
A56: Camila Cristiane Pereira dos Santos | B56: cd
A57: Camila Ferreira Carmona | B57: ca | C57: CAMILA CARMONA/ARQUIVO DA EDITORA
A58: Carlitos Pinheiro | B58: cq | C58: CARLITOS PINHEIRO/ARQUIVO DA EDITORA
A59: Carlos Alberto Borin Junior | B59: cj | C59: CARLOS BORIN/ARQUIVO DA EDITORA
A60: Carlos Eduardo Nascimento | B60: cn | C60: CARLOS EDUARDO NASCIMENTO/ARQUIVO DA EDITORA
A61: Carmen Ferreira Martinez | B61: cc | C61: CARMEN MARTINEZ/ARQUIVO DA EDITORA
A62: Carol Rempto | B62: cw | C62: CAROL REMPTO/ARQUIVO DA EDITORA
A63: Carol Sartori | B63: cx | C63: CAROL SARTORI/ARQUIVO DA EDITORA
A64: Carolina Coroa | B64: kk | C64: CAROLINA COROA/ARQUIVO DA EDITORA
A65: Caroline Romão Bezerra | B65: co | C65: CAROLINE ROMÃO BEZERRA/ARQUIVO DA EDITORA
A66: Cartoon Pro | B66: cp
A67: Cássio Bittencourt | B67: cs | C67: CÁSSIO BITTENCOURT/ARQUIVO DA EDITORA
A68: Cássio Yoshiyaki Shibukawa | B68: cy | C68: CÁSSIO YOSHIYAKI SHIBUKAWA/ARQUIVO DA EDITORA
A69: Cátia Germani | B69: cm | C69: CÁTIA GERMANI/ARQUIVO DA EDITORA
A70: Cauê Zunchini | B70: ci | C70: CAUÊ ZUNCHINI/ARQUIVO DA EDITORA
A71: Cecilia Andrade | B71: cl | C71: CECILIA ANDRADE/ARQUIVO DA EDITORA
A72: Chanceler | B72: ch
A73: Chris Borges | B73: cg | C73: CHRIS BORGES/ARQUIVO DA EDITORA
A74: Clarissa França | B74: cf | C74: CLARISSA FRANÇA/ARQUIVO DA EDITORA
A75: Claudia Brito | B75: cb | C75: CLAUDIA BRITO/ARQUIVO DA EDITORA
A76: Claudia Souza | B76: cz | C76: CLAUDIA SOUZA/ARQUIVO DA EDITORA
A77: Copa Studio | B77: ap
A78: Cria Ideias | B78: cr
A79: Cris Eich (Maria Cristina Pires de Carvalho) | B79: ce | C79: CRIS EICH/ARQUIVO DA EDITORA
A80: Cynthia Sekiguchi | B80: ck | C80: CYNTHIA SEKIGUCHI/ARQUIVO DA EDITORA
A81: Dani Mota | B81: dm | C81: DANI MOTA/ARQUIVO DA EDITORA
A82: Daniel Araujo | B82: da | C82: DANIEL ARAUJO/ARQUIVO DA EDITORA
A83: Daniel Carvalho | B83: dc | C83: DANIEL CARVALHO/ARQUIVO DA EDITORA
A84: Daniel Wu | B84: dw | C84: DANIEL WU/ARQUIVO DA EDITORA
A85: Daniel Zeppo | B85: dz | C85: DANIEL GUSTAVO SILVA GONÇALVES/ARQUIVO DA EDITORA
A86: Danielle Pioli | B86: dp | C86: DANIELLE PIOLI/ARQUIVO DA EDITORA
A87: Danillo Souza | B87: dl | C87: DANILLO SOUZA/ARQUIVO DA EDITORA
A88: Danilo Santos - Red Dragon | B88: dd | C88: DANILO SANTOS/ARQUIVO DA EDITORA
A89: Davi Augusto | B89: do | C89: DAVI AUGUSTO/ARQUIVO DA EDITORA
A90: David Renó | B90: dv | C90: DAVI RENÓ/ARQUIVO DA EDITORA
... A108: Erika Lourenço | B108: ek | C108: ERIKA LOURENÇO/ARQUIVO DA EDITORA
A109: Estúdio Amplarena | B109: al
A110: Estúdio Guerra | B110: eg
A111: Estúdio Ilustranet | B111: it | C111: RUBENS TAVARES LIMA FILHO/ARQUIVO DA EDITORA
A112: Estúdio Kiwi | B112: kw | C112: THIAGO LOPES/ARQUIVO DA EDITORA
A113: Estúdio Lab307 | B113: lb | C113: ERIK MALAGRINO/ARQUIVO DA EDITORA
A114: Estúdio Meraki | B114: mk | C114: NATANAELE BILMAIA/ARQUIVO DA EDITORA
A115: Estúdio Mil | B115: em
A116: Estúdio Orangotango | B116: eo
A117: Estúdio Ornitorrinco | B117: ec | C117: MÁRCIO GUERRA/ARQUIVO DA EDITORA
A118: Estúdio Um mais Dois | B118: ud
A119: Ezequiel Silva (Monge Lua) | B119: ez | C119: EZEQUIEL SILVA/ARQUIVO DA EDITORA
A120: Ewerton Xavier | B120: ex | C120: EWERTON XAVIER/ARQUIVO DA EDITORA
A121: Fabio Eugenio | B121: fe | C121: FABIO EUGENIO/ARQUIVO DA EDITORA
A122: Fabíola Petri | B122: fp | C122: FABÍOLA PETRI/ARQUIVO DA EDITORA
A123: Felipe Grigoli | B123: fg | C123: FELIPE GRIGOLI/ARQUIVO DA EDITORA
A124: Fernanda Monteiro | B124: fm | C124: FERNANDA MONTEIRO/ARQUIVO DA EDITORA
A125: Fernanda Pardini Biagio | B125: fb | C125: FERNANDA PARDINI BIAGIO/ARQUIVO DA EDITORA
A126: Flávia Nunes | B126: fn | C126: FLÁVIA NUNES/ARQUIVO DA EDITORA
A127: Flavio Roberto Pereira | B127: fl | C127: FLAVIO PEREIRA/ARQUIVO DA EDITORA
A128: Francine Matsumoto | B128: fr | C128: FRAN MATSUMOTO/ARQUIVO DA EDITORA
A129: Gabi Vasko | B129: gv | C129: GABI VASKO/ARQUIVO DA EDITORA
A130: Gabriel Kyu | B130: gk | C130: GABRIEL KYU/ARQUIVO DA EDITORA
... A138: Giully Leão | B138: gy | C138: GIULLY LEÃO/ARQUIVO DA EDITORA
A139: Giz de Cera Studio | B139: gz
A140: Graphorama | B140: gh
A141: Graziela Andrade | B141: ge | C141: GRAZIELA ANDRADE/ARQUIVO DA EDITORA
A142: Guilherme Aranega - Estudio Rufus | B142: gn | C142: GUILHERME ARANEGA/ARQUIVO DA EDITORA
A143: Guilherme Casagrandi | B143: gg | C143: GUILHERME CASAGRANDI/ARQUIVO DA EDITORA
A144: Guilherme Da Cas | B144: gc | C144: GUILHERME DA CAS/ARQUIVO DA EDITORA
A145: Gustavo Conti | B145: gu | C145: GUSTAVO CONTI/ARQUIVO DA EDITORA
A146: Gustavo Pedrosa | B146: gp | C146: GUSTAVO PEDROSA/ARQUIVO DA EDITORA
A147: Gustavo Ramos | B147: gr | C147: GUSTAVO RAMOS/ARQUIVO DA EDITORA
A148: Heloísa Pintarelli | B148: he | C148: HELOÍSA PINTARELLI/ARQUIVO DA EDITORA
A149: Henrique Dan Fuzitani | B149: hf | C149: HENRIQUE DAN FUZITANI/ARQUIVO DA EDITORA
A150: Henrique Jorge | B150: hj | C150: HENRIQUE JORGE G. M. SILVA/ARQUIVO DA EDITORA
A151: Hiro Kawahara | B151: hk | C151: HIRO KAWAHARA/ARQUIVO DA EDITORA
...

Sheet metadados
A1: PRÉ-EDIÇÃO | B1: ILUSTRAÇÃO | C1: CAPA | D1: 1 | E1: AJUSTE | F1: SCRIBA | G1: 1 | H1: PREVISAO
A2: EDICAO_EQUIPE | B2: IL TEC ARTE | C2: APRESENT. | D2: 2 | E2: NOVA | F2: FTD | G2: 2 | H2: FINALIZADO
A3: EDICAO_ARTE | B3: IL + FOTO | C3: SUMÁRIO | D3: 3 | E3: RESGATE | F3: MDN | G3: 3 | H3: FINALIZADO RAFE
A4: ILUSTRANDO | B4: MAPA | C4: ABERTURA | D4: 4 | F4: SABER | G4: 4 | H4: PAGO
A5: AVALIANDO | B5: GRÁFICO | C5: MIOLO | D5: 5 | F5: SM | G5: 5 | H5: PAGO RAFE
A6: AJUSTANDO | B6: LINHA TEMPO | C6: PAG.ESPECIAL | D6: 6 | F6: SCP | G6: 6
A7: FINALIZANDO | B7: INFOGRÁFICO | C7: MP-G | D7: ÚNICO | F7: ABR | G7: 7
A8: PRONTA | C8: MP-E | F8: BASE | G8: 8
A9: APLICADA | F9: IBEP | G9: 9
A10: EXCLUIDA | F10: LEYA | G10: 10
F11: SARAIVA | G11: 11
F12: SANTILLANA | G12: 12
F13: QUINTETO | G13: 13
G14: 14
